{"status": "OK", "html_attributions": [], "results": [{"rating": 4.4, "user_ratings_total": 10, "name": "Wazirpur Flyover", "reference": "ChIJ4Ws2YTECDTkR1QBDmoKi5Fo", "geometry": {"location": {"lat": 28.692421, "lng": 77.15365}, "viewport": {"northeast": {"lat": 28.6937581302915, "lng": 77.1550366302915}, "southwest": {"lat": 28.6910601697085, "lng": 77.15233866970848}}}, "place_id": "ChIJ4Ws2YTECDTkR1QBDmoKi5Fo", "plus_code": {"global_code": "7JWVM5R3+XF", "compound_code": "M5R3+XF New Delhi, Delhi, India"}, "vicinity": "Block C5, Keshav Puram, Tri Nagar, New Delhi", "photos": [{"photo_reference": "ATtYBwJSaqxDCER0O1z8Zr_prw1TbE_fxtayeOzMBoDIg97LQnKGOm57fIibQ56Nlk7AWtebVqAFVqLm2DfpXVbQPmUyp6cravfsaDoZVXkO26oCGu1fsNrvUan6OJCwYjPxdRYbn80Ndz7FUZMkNzKMQp-pjIxk660SllbmmHTUe6viZQLx", "width": 1775, "html_attributions": ["<a href=\"https://maps.google.com/maps/contrib/114754091124761744850\">Rippy Bedi</a>"], "height": 932}], "scope": "GOOGLE", "business_status": "OPERATIONAL", "types": ["bus_station", "transit_station", "point_of_interest", "establishment"], "icon": "https://maps.gstatic.com/mapfiles/place_api/icons/v1/png_71/bus-71.png"}, {"rating": 3.5, "user_ratings_total": 14, "name": "Punjabi Bagh Terminal", "reference": "ChIJB6-eV68DDTkRMXVQrky6srU", "geometry": {"location": {"lat": 28.66797500000001, "lng": 77.13718}, "viewport": {"northeast": {"lat": 28.6692834302915, "lng": 77.1384957302915}, "southwest": {"lat": 28.66658546970851, "lng": 77.13579776970849}}}, "place_id": "ChIJB6-eV68DDTkRMXVQrky6srU", "plus_code": {"global_code": "7JWVM49P+5V", "compound_code": "M49P+5V New Delhi, Delhi, India"}, "vicinity": "Main Patel Road, Punjabi Bagh Cooperative Housing Soceity, East Punjabi Bagh, Punjabi Bagh, New Delhi", "photos": [{"photo_reference": "ATtYBwL0fIi4rl84TaiIEZx5l0gnQaBiJysyJRnub0VbHrYriEGxqajf-HqoNoqf1l-P4hzZDB3tODdl2Y7vSxykbNHy8LbZmQvBZK0xblNq0vUV7rUuF9cQ58znA70CMOayDX79IlkZmYnFp5K1NsNY3d1SBkIDzcQY6WWP1OFJ-ySKeR-D", "width": 3264, "html_attributions": ["<a href=\"https://maps.google.com/maps/contrib/113976679846204625095\">Sam k soni</a>"], "height": 2448}], "scope": "GOOGLE", "business_status": "OPERATIONAL", "types": ["bus_station", "transit_station", "point_of_interest", "establishment"], "icon": "https://maps.gstatic.com/mapfiles/place_api/icons/v1/png_71/bus-71.png"}, {"name": "Brittania Chowk", "reference": "ChIJ6_yBH7QDDTkRy-ugPWr-xh4", "geometry": {"location": {"lat": 28.6807136, "lng": 77.1429428}, "viewport": {"northeast": {"lat": 28.6817551302915, "lng": 77.14437943029151}, "southwest": {"lat": 28.6790571697085, "lng": 77.14168146970849}}}, "place_id": "ChIJ6_yBH7QDDTkRy-ugPWr-xh4", "plus_code": {"global_code": "7JWVM4JV+75", "compound_code": "M4JV+75 Delhi, India"}, "vicinity": "India", "scope": "GOOGLE", "business_status": "OPERATIONAL", "types": ["bus_station", "transit_station", "point_of_interest", "establishment"], "icon": "https://maps.gstatic.com/mapfiles/place_api/icons/v1/png_71/bus-71.png"}, {"rating": 3.7, "user_ratings_total": 23, "name": "Wazirpur Depot", "reference": "ChIJDz3X9zMCDTkRRsqCw_8tgRg", "geometry": {"location": {"lat": 28.691929, "lng": 77.153401}, "viewport": {"northeast": {"lat": 28.6932637302915, "lng": 77.1548191302915}, "southwest": {"lat": 28.6905657697085, "lng": 77.1521211697085}}}, "place_id": "ChIJDz3X9zMCDTkRRsqCw_8tgRg", "plus_code": {"global_code": "7JWVM5R3+Q9", "compound_code": "M5R3+Q9 New Delhi, Delhi, India"}, "vicinity": "Ring Road, Netaji Subhash Place, Pitam Pura, New Delhi", "photos": [{"photo_reference": "ATtYBwIgKZ7-aLXxl2MS7Vj-Th209VW5RINHVt1Io8CMnhx1E2FrPIan4ou7wzJuADxCae4NPUOn0Gp9UKA1TH6LHrX4W6_P1w2xVXZm8eLCZePKQkBJ9T8W6saFCgCSacH9rxy59YL8L_7mxSwm3np6820ebA4DsYUc3pWf_aHQRfX-Pz9C", "width": 4608, "html_attributions": ["<a href=\"https://maps.google.com/maps/contrib/117291400439171850169\">Manpreet Singh</a>"], "height": 2592}], "scope": "GOOGLE", "business_status": "OPERATIONAL", "types": ["bus_station", "transit_station", "point_of_interest", "establishment"], "icon": "https://maps.gstatic.com/mapfiles/place_api/icons/v1/png_71/generic_business-71.png"}, {"rating": 4.3, "user_ratings_total": 3, "name": "Kohat Enclave Metro Station (Opposite)", "reference": "ChIJHW3t7tEDDTkRk5Iiq2RiV8Y", "geometry": {"location": {"lat": 28.6973629, "lng": 77.1418152}, "viewport": {"northeast": {"lat": 28.69869363029149, "lng": 77.1431541802915}, "southwest": {"lat": 28.69599566970849, "lng": 77.14045621970848}}}, "place_id": "ChIJHW3t7tEDDTkRk5Iiq2RiV8Y", "plus_code": {"global_code": "7JWVM4WR+WP", "compound_code": "M4WR+WP Delhi, India"}, "vicinity": "India", "scope": "GOOGLE", "business_status": "OPERATIONAL", "types": ["bus_station", "transit_station", "point_of_interest", "establishment"], "icon": "https://maps.gstatic.com/mapfiles/place_api/icons/v1/png_71/bus-71.png"}, {"rating": 3.8, "user_ratings_total": 49, "name": "Kohat Enclave (Metro Stn.)", "reference": "ChIJD92M8dEDDTkR5r8_HihQGlw", "geometry": {"location": {"lat": 28.697457, "lng": 77.14209799999999}, "viewport": {"northeast": {"lat": 28.6987766302915, "lng": 77.14343593029149}, "southwest": {"lat": 28.69607866970851, "lng": 77.14073796970848}}}, "place_id": "ChIJD92M8dEDDTkR5r8_HihQGlw", "plus_code": {"global_code": "7JWVM4WR+XR", "compound_code": "M4WR+XR Delhi, India"}, "vicinity": "India", "photos": [{"photo_reference": "ATtYBwL6evBI-_lURrA08vuc9kRU12C3T13YoBfMmFlvyJy1m3ZasxJuRKtsfeOyYK2RyO7FZiMvlRX5RVwoNiR7EHZmOXQtpKIGp8atTSBFyFE2fYaI_EWfIGVTe8wlGHiDa-okbYfdKh3wxURGcTOTUTyR8sjPxuBeGgjFiZTYyhQLkPPa", "width": 4032, "html_attributions": ["<a href=\"https://maps.google.com/maps/contrib/111678449104821789295\">Kamlesh Sharma</a>"], "height": 3024}], "scope": "GOOGLE", "business_status": "OPERATIONAL", "types": ["bus_station", "transit_station", "point_of_interest", "establishment"], "icon": "https://maps.gstatic.com/mapfiles/place_api/icons/v1/png_71/bus-71.png"}, {"rating": 3.6, "user_ratings_total": 8, "name": "Kohat Enclave Metro Station", "reference": "ChIJT5PGsNEDDTkRPrlMlW9ai6A", "geometry": {"location": {"lat": 28.6978986, "lng": 77.1409173}, "viewport": {"northeast": {"lat": 28.6993262802915, "lng": 77.1424286302915}, "southwest": {"lat": 28.6966283197085, "lng": 77.1397306697085}}}, "place_id": "ChIJT5PGsNEDDTkRPrlMlW9ai6A", "plus_code": {"global_code": "7JWVM4XR+59", "compound_code": "M4XR+59 Delhi, India"}, "vicinity": "India", "photos": [{"photo_reference": "ATtYBwJNqwZfC5tsGhCfhzLed44zvbiHEFje-D85PJTO7cXiM6pdBnTj-XyMYovZsUS1W26VMdcdFzSsK1B1LVYxu8I7K0vMqbIT2PvWmXC8mln8r5QMkyRIhv3vqus16bBG43dAZdhKMi4ZsgZ0B6CuB2nCUpU61nR6MiWs7eJCDKpWdK68", "width": 3264, "html_attributions": ["<a href=\"https://maps.google.com/maps/contrib/102996584767109342232\">TrainFeed</a>"], "height": 2448}], "scope": "GOOGLE", "business_status": "OPERATIONAL", "types": ["bus_station", "transit_station", "point_of_interest", "establishment"], "icon": "https://maps.gstatic.com/mapfiles/place_api/icons/v1/png_71/bus-71.png"}, {"name": "ND/DP Block Bus stand pitampura", "reference": "ChIJAYrprdMDDTkRKof_Mk5EtRc", "geometry": {"location": {"lat": 28.6998486, "lng": 77.1450041}, "viewport": {"northeast": {"lat": 28.7012165302915, "lng": 77.14635578029151}, "southwest": {"lat": 28.6985185697085, "lng": 77.1436578197085}}}, "place_id": "ChIJAYrprdMDDTkRKof_Mk5EtRc", "plus_code": {"global_code": "7JWVM4XW+W2", "compound_code": "M4XW+W2 Delhi, India"}, "vicinity": "India", "scope": "GOOGLE", "business_status": "OPERATIONAL", "types": ["bus_station", "transit_station", "point_of_interest", "establishment"], "icon": "https://maps.gstatic.com/mapfiles/place_api/icons/v1/png_71/bus-71.png"}, {"rating": 3.9, "user_ratings_total": 39, "name": "B-4 Keshav Puram", "reference": "ChIJ56mbSjgCDTkRAoqFP79qlyA", "geometry": {"location": {"lat": 28.687551, "lng": 77.162475}, "viewport": {"northeast": {"lat": 28.68889848029151, "lng": 77.1638049802915}, "southwest": {"lat": 28.68620051970851, "lng": 77.1611070197085}}}, "opening_hours": {"open_now": false}, "place_id": "ChIJ56mbSjgCDTkRAoqFP79qlyA", "plus_code": {"global_code": "7JWVM5Q6+2X", "compound_code": "M5Q6+2X New Delhi, Delhi, India"}, "vicinity": "Keshav Puram, \u092e\u0939\u093e\u0930\u093e\u091c\u093e \u0928\u093e\u0939\u0930 \u0938\u093f\u0902\u0939 \u092e\u093e\u0930\u094d\u0917, Pocket F, Phase 1, Ashok Vihar, New Delhi", "photos": [{"photo_reference": "ATtYBwIYVBwkeMqlFvefXpo3oWJ2LA8fwO_r54tpKrdhQMohcwimv_dJuqFsIwCUlxEXSn_zhFcLXC7dfNXyuvVL9enN3kXSMbN9fIJYIEjaf4tMiX6B2hGgBBFPPW7EWroDbfXHZHensHPTgpRZcDr7-YmKwmu1ITmf0aoekd9FezOqg4K6", "width": 3096, "html_attributions": ["<a href=\"https://maps.google.com/maps/contrib/111920615551666777368\">Aman Kashyap</a>"], "height": 4128}], "scope": "GOOGLE", "business_status": "OPERATIONAL", "types": ["bus_station", "transit_station", "point_of_interest", "establishment"], "icon": "https://maps.gstatic.com/mapfiles/place_api/icons/v1/png_71/bus-71.png"}, {"name": "Gulab Sweets", "reference": "ChIJ7xyRm9ADDTkR4UP2F0gm_I8", "geometry": {"location": {"lat": 28.69978160000001, "lng": 77.1374305}, "viewport": {"northeast": {"lat": 28.7011294802915, "lng": 77.1387785302915}, "southwest": {"lat": 28.6984315197085, "lng": 77.1360805697085}}}, "place_id": "ChIJ7xyRm9ADDTkR4UP2F0gm_I8", "plus_code": {"global_code": "7JWVM4XP+WX", "compound_code": "M4XP+WX Delhi, India"}, "vicinity": "India", "scope": "GOOGLE", "business_status": "OPERATIONAL", "types": ["bus_station", "transit_station", "point_of_interest", "establishment"], "icon": "https://maps.gstatic.com/mapfiles/place_api/icons/v1/png_71/bus-71.png"}, {"rating": 3, "user_ratings_total": 1, "name": "Punjabi Bagh Terminal", "reference": "ChIJLRuXVa8DDTkRxQzPTmJNnRE", "geometry": {"location": {"lat": 28.667471, "lng": 77.13710859999999}, "viewport": {"northeast": {"lat": 28.66884398029149, "lng": 77.1384810802915}, "southwest": {"lat": 28.6661460197085, "lng": 77.13578311970849}}}, "place_id": "ChIJLRuXVa8DDTkRxQzPTmJNnRE", "plus_code": {"global_code": "7JWVM48P+XR", "compound_code": "M48P+XR New Delhi, Delhi, India"}, "vicinity": "Main Patel Road, JJ Colony, Moti Nagar, New Delhi", "photos": [{"photo_reference": "ATtYBwLWHZIU8uTfwlRe8nqaOfQHUdJ3Q_kFO-8Pasy6o8FYlqG4G-WbBv04ALRKXBV2UP0AF9SjNJkkmuCWpCE-ThdAyvlozbHqQ_p-3B-HdhdwG8gFerBAR8c_yUOiKTczRX219-WXbbur_6jqptPqBUvKGttNGXwH21pZDS1x0x_t4UVI", "width": 1024, "html_attributions": ["<a href=\"https://maps.google.com/maps/contrib/102964426889211851492\">Raju Bhatia</a>"], "height": 768}], "scope": "GOOGLE", "business_status": "OPERATIONAL", "types": ["bus_station", "transit_station", "point_of_interest", "establishment"], "icon": "https://maps.gstatic.com/mapfiles/place_api/icons/v1/png_71/bus-71.png"}]}