{"status": "OK", "html_attributions": [], "results": [{"name": "ERSHAD KHAN village Udaka", "reference": "ChIJ2TQhQTgvDTkRWw2zMEQAfAQ", "geometry": {"location": {"lat": 28.2196751, "lng": 77.09762649999999}, "viewport": {"northeast": {"lat": 28.2210310802915, "lng": 77.09897578029151}, "southwest": {"lat": 28.21833311970849, "lng": 77.0962778197085}}}, "opening_hours": {"open_now": true}, "place_id": "ChIJ2TQhQTgvDTkRWw2zMEQAfAQ", "plus_code": {"global_code": "7JWV639X+V3", "compound_code": "639X+V3 Udaka, Haryana, India"}, "vicinity": "Government School Road, Udaka", "photos": [{"photo_reference": "CmRaAAAAo8NIbIZDstjOZUyuFSAg30xl2UjdqbEoALBTN17yqBjTrDhfU5KhOnVhwuDQwQWtz5KODYjx7Hx1RxphOnMh3T9QLrJtoHO1DOI9rxDof3P5_004kUcHqgOpTTpsbrMyEhAeLxfDFYb_ZMpHZPQbeoYxGhT-av7B_QfqzFJ_jIOzMQ3Ov_oFnQ", "width": 520, "html_attributions": ["<a href=\"https://maps.google.com/maps/contrib/113111550404551129145\">Ajay shukla GKP</a>"], "height": 1040}], "scope": "GOOGLE", "business_status": "OPERATIONAL", "types": ["doctor", "health", "point_of_interest", "establishment"], "icon": "https://maps.gstatic.com/mapfiles/place_api/icons/v1/png_71/generic_business-71.png"}]}