{"status": "OK", "html_attributions": [], "results": [{"rating": 4.4, "user_ratings_total": 13, "name": "Police Station Bawana", "reference": "ChIJq6tnfRGoDTkRwCUC4Eu9m88", "geometry": {"location": {"lat": 28.806138, "lng": 77.0229591}, "viewport": {"northeast": {"lat": 28.8076568802915, "lng": 77.0243759302915}, "southwest": {"lat": 28.8049589197085, "lng": 77.02167796970849}}}, "opening_hours": {"open_now": true}, "place_id": "ChIJq6tnfRGoDTkRwCUC4Eu9m88", "plus_code": {"global_code": "7JWVR24F+F5", "compound_code": "R24F+F5 Delhi, India"}, "vicinity": "Auchandi Bawana Road, Bawana, Delhi", "photos": [{"photo_reference": "ATtYBwJsfNXq7RX4jxRj0wdqleUweBXpXxUYzryUaMTXh9kQXzPRjA9dUNGVN3GiLJ8rBny3W5SVUJghhZkiy2j6kEvIZu8ThsG5GHrGR00ellQq6yfNOUG-_nky2WRfzLPCFXv-xb7szvP7ViHBmP9aZDJi6hzU21iglu7KFq57rbJZuPZN", "width": 1836, "html_attributions": ["<a href=\"https://maps.google.com/maps/contrib/103051401578634898677\">PINKU KUMAR</a>"], "height": 3264}], "scope": "GOOGLE", "business_status": "OPERATIONAL", "types": ["police", "point_of_interest", "establishment"], "icon": "https://maps.gstatic.com/mapfiles/place_api/icons/v1/png_71/police-71.png"}, {"name": "Dariya Pur Police Post", "reference": "ChIJ07a5EBKoDTkRoiJet1w7lj8", "geometry": {"location": {"lat": 28.8059655, "lng": 77.0229296}, "viewport": {"northeast": {"lat": 28.8075652302915, "lng": 77.02437873029152}, "southwest": {"lat": 28.8048672697085, "lng": 77.0216807697085}}}, "opening_hours": {"open_now": true}, "place_id": "ChIJ07a5EBKoDTkRoiJet1w7lj8", "plus_code": {"global_code": "7JWVR24F+95", "compound_code": "R24F+95 Delhi, India"}, "vicinity": "Darayapur Kalan Village, Delhi", "scope": "GOOGLE", "business_status": "OPERATIONAL", "types": ["police", "point_of_interest", "establishment"], "icon": "https://maps.gstatic.com/mapfiles/place_api/icons/v1/png_71/police-71.png"}]}