{"status": "OK", "html_attributions": [], "results": [{"rating": 5, "user_ratings_total": 1, "name": "Satyam Path Lab", "reference": "ChIJjxohGZ2rDTkRf60g0_y1wLU", "geometry": {"location": {"lat": 28.8261318, "lng": 77.1759373}, "viewport": {"northeast": {"lat": 28.8275142802915, "lng": 77.1773223802915}, "southwest": {"lat": 28.8248163197085, "lng": 77.1746244197085}}}, "opening_hours": {"open_now": true}, "place_id": "ChIJjxohGZ2rDTkRf60g0_y1wLU", "plus_code": {"global_code": "7JWVR5GG+F9", "compound_code": "R5GG+F9 Delhi, India"}, "vicinity": "Palla Bakhtawarpur Road, Bakhtawar Pur Village, Delhi", "photos": [{"photo_reference": "ATtYBwL4FqWX2d2mp7_OegpnAS80TSTUzPohoDVgpv0Ig14o-PVMFv6ELDjkG5KNfFk5yj5Xtp5KP48BhLOChRmR0k75tg1GxigPYi7Rtq_pJ1anQBeCWRSkqbxGVP9_2tKRv71WmKbaWcEJMMQweHVRTcuG3ej0XhkkzJT1jbf4pCBRU2-N", "width": 720, "html_attributions": ["<a href=\"https://maps.google.com/maps/contrib/114419720015881273575\">Satyam Path Lab</a>"], "height": 1280}], "scope": "GOOGLE", "business_status": "OPERATIONAL", "types": ["hospital", "doctor", "health", "point_of_interest", "establishment"], "icon": "https://maps.gstatic.com/mapfiles/place_api/icons/v1/png_71/generic_business-71.png"}, {"rating": 5, "user_ratings_total": 21, "name": "AYUSH HEALTHCARE", "reference": "ChIJ3SzuIWCrDTkRpS8-IbR24cA", "geometry": {"location": {"lat": 28.8260355, "lng": 77.1749609}, "viewport": {"northeast": {"lat": 28.82733408029149, "lng": 77.17631893029152}, "southwest": {"lat": 28.82463611970849, "lng": 77.1736209697085}}}, "opening_hours": {"open_now": true}, "place_id": "ChIJ3SzuIWCrDTkRpS8-IbR24cA", "plus_code": {"global_code": "7JWVR5GF+CX", "compound_code": "R5GF+CX Delhi, India"}, "vicinity": "Bakhtawar Pur, Bakhtawar Pur Village, Delhi", "scope": "GOOGLE", "business_status": "OPERATIONAL", "types": ["doctor", "health", "point_of_interest", "establishment"], "icon": "https://maps.gstatic.com/mapfiles/place_api/icons/v1/png_71/generic_business-71.png"}, {"rating": 3.5, "user_ratings_total": 4, "name": "Dr. J. P. Khandelwal", "reference": "ChIJHY53c8CqDTkRb_MdzH-Myc0", "geometry": {"location": {"lat": 28.8259479, "lng": 77.1749086}, "viewport": {"northeast": {"lat": 28.82730558029151, "lng": 77.17625598029151}, "southwest": {"lat": 28.82460761970851, "lng": 77.17355801970851}}}, "opening_hours": {"open_now": true}, "place_id": "ChIJHY53c8CqDTkRb_MdzH-Myc0", "plus_code": {"global_code": "7JWVR5GF+9X", "compound_code": "R5GF+9X Delhi, India"}, "vicinity": "Kasturba Market, Bakhtawar Pur, Bakhtawar Pur Village, Delhi", "photos": [{"photo_reference": "ATtYBwI7nZD8xFNNsQFWvJTn8rqGFKgmoDIe3cicYl3IRkKcxnfP1JvaJ5Y1J8qSduMT4yyhmZu2vwTOCI43y2WqH0pq-rNhFoLtNmBidvGaIcUJ5fEXfm1iShwu5bz2IElaJSSl_5LQV5MDE8T8Q8ts5PmRedK0LZMw4usi9mYYGbhppYkW", "width": 3264, "html_attributions": ["<a href=\"https://maps.google.com/maps/contrib/110838591840260632819\">Sachin Arora</a>"], "height": 2448}], "scope": "GOOGLE", "business_status": "OPERATIONAL", "types": ["doctor", "health", "point_of_interest", "establishment"], "icon": "https://maps.gstatic.com/mapfiles/place_api/icons/v1/png_71/generic_business-71.png"}, {"name": "Khan clinic", "reference": "ChIJoZrkAMOrDTkRykboI1wGDz8", "geometry": {"location": {"lat": 28.823675, "lng": 77.1722345}, "viewport": {"northeast": {"lat": 28.8250357302915, "lng": 77.17350448029151}, "southwest": {"lat": 28.8223377697085, "lng": 77.1708065197085}}}, "place_id": "ChIJoZrkAMOrDTkRykboI1wGDz8", "plus_code": {"global_code": "7JWVR5FC+FV", "compound_code": "R5FC+FV Delhi, India"}, "vicinity": "Bakhtawar Pur, Bakhtawar Pur Village, Delhi", "scope": "GOOGLE", "business_status": "OPERATIONAL", "types": ["doctor", "health", "point_of_interest", "establishment"], "icon": "https://maps.gstatic.com/mapfiles/place_api/icons/v1/png_71/generic_business-71.png"}, {"name": "Anubhav Lab", "reference": "ChIJB6mZS6qrDTkRssrrEQL3ioI", "geometry": {"location": {"lat": 28.8237009, "lng": 77.1719794}, "viewport": {"northeast": {"lat": 28.82503073029151, "lng": 77.1733272802915}, "southwest": {"lat": 28.82233276970851, "lng": 77.1706293197085}}}, "opening_hours": {"open_now": true}, "place_id": "ChIJB6mZS6qrDTkRssrrEQL3ioI", "plus_code": {"global_code": "7JWVR5FC+FQ", "compound_code": "R5FC+FQ Delhi, India"}, "vicinity": "near chhotu ram public school, Bakhtawar Pur, Delhi", "scope": "GOOGLE", "business_status": "OPERATIONAL", "types": ["doctor", "health", "point_of_interest", "establishment"], "icon": "https://maps.gstatic.com/mapfiles/place_api/icons/v1/png_71/generic_business-71.png"}, {"rating": 5, "user_ratings_total": 2, "name": "Bakhtawarpur Diagnostic Centre", "reference": "ChIJnVIYPQCrDTkRALfUy4oTAlo", "geometry": {"location": {"lat": 28.8236828, "lng": 77.171972}, "viewport": {"northeast": {"lat": 28.8250791302915, "lng": 77.1733098302915}, "southwest": {"lat": 28.8223811697085, "lng": 77.17061186970848}}}, "opening_hours": {"open_now": true}, "place_id": "ChIJnVIYPQCrDTkRALfUy4oTAlo", "plus_code": {"global_code": "7JWVR5FC+FQ", "compound_code": "R5FC+FQ Delhi, India"}, "vicinity": "Unnamed Road, Bakhtawar Pur, Bakhtawarpur, Delhi", "photos": [{"photo_reference": "ATtYBwIY3q77iqeBvIBg6VlyCm9Gx70zenP80P9dvHIluH-22prMv80AI-f3GMg8ae22hFMz4mdQs_EZtGoSJZxwtjLqpR9vkuWQAqlztX6VKZ3SYzZvev72kAI6IN4u231rLdSVaragkDbiDM16GDkECt0OmsXn80mYO-4kXOXSR3oJgYX9", "width": 500, "html_attributions": ["<a href=\"https://maps.google.com/maps/contrib/115586086611169160601\">Sudhirshri Kumar</a>"], "height": 500}], "scope": "GOOGLE", "business_status": "OPERATIONAL", "types": ["doctor", "health", "point_of_interest", "establishment"], "icon": "https://maps.gstatic.com/mapfiles/place_api/icons/v1/png_71/generic_business-71.png"}, {"rating": 5, "user_ratings_total": 3, "name": "Prameet Chikitsa Kendra", "reference": "ChIJqwdQfZWqDTkRIL0AErMuVwM", "geometry": {"location": {"lat": 28.822854, "lng": 77.171758}, "viewport": {"northeast": {"lat": 28.8241909802915, "lng": 77.17318113029151}, "southwest": {"lat": 28.8214930197085, "lng": 77.1704831697085}}}, "opening_hours": {"open_now": true}, "place_id": "ChIJqwdQfZWqDTkRIL0AErMuVwM", "plus_code": {"global_code": "7JWVR5FC+4P", "compound_code": "R5FC+4P Delhi, India"}, "vicinity": "Opposite AXIS BANK ATM Near Subhash Chowk, Bakhtawrpur Village, Delhi", "scope": "GOOGLE", "business_status": "OPERATIONAL", "types": ["doctor", "health", "point_of_interest", "establishment"], "icon": "https://maps.gstatic.com/mapfiles/place_api/icons/v1/png_71/generic_business-71.png"}, {"name": "Adarsh health care medical centre", "reference": "ChIJWyP9ZRyrDTkR8goEVirvW0s", "geometry": {"location": {"lat": 28.8219646, "lng": 77.171236}, "viewport": {"northeast": {"lat": 28.8233135802915, "lng": 77.1725849802915}, "southwest": {"lat": 28.8206156197085, "lng": 77.1698870197085}}}, "place_id": "ChIJWyP9ZRyrDTkR8goEVirvW0s", "plus_code": {"global_code": "7JWVR5CC+QF", "compound_code": "R5CC+QF Delhi, India"}, "vicinity": "Palla Bakhtawarpur Road, Bakhtawar Pur Village, Delhi", "scope": "GOOGLE", "business_status": "OPERATIONAL", "types": ["doctor", "health", "point_of_interest", "establishment"], "icon": "https://maps.gstatic.com/mapfiles/place_api/icons/v1/png_71/generic_business-71.png"}]}