{"status": "OK", "html_attributions": [], "results": [{"name": "Bhola Dr C L", "reference": "ChIJq6qq9v-mDTkRaMdUPInb5oM", "geometry": {"location": {"lat": 28.8291663, "lng": 76.9639122}, "viewport": {"northeast": {"lat": 28.83047038029149, "lng": 76.9652284302915}, "southwest": {"lat": 28.8277724197085, "lng": 76.96253046970848}}}, "place_id": "ChIJq6qq9v-mDTkRaMdUPInb5oM", "plus_code": {"global_code": "7JWRRXH7+MH", "compound_code": "RXH7+MH Garhi, Delhi, India"}, "vicinity": "86, Amrit Puri, Garhi, Amrit Puri, New Delhi", "scope": "GOOGLE", "business_status": "OPERATIONAL", "types": ["doctor", "health", "point_of_interest", "establishment"], "icon": "https://maps.gstatic.com/mapfiles/place_api/icons/v1/png_71/generic_business-71.png"}, {"name": "S.K Medical Store", "reference": "ChIJ929OM_amDTkRfbonEPS0dBQ", "geometry": {"location": {"lat": 28.8423084, "lng": 76.96327930000001}, "viewport": {"northeast": {"lat": 28.8436944302915, "lng": 76.9646786302915}, "southwest": {"lat": 28.8409964697085, "lng": 76.9619806697085}}}, "place_id": "ChIJ929OM_amDTkRfbonEPS0dBQ", "plus_code": {"global_code": "7JWRRXR7+W8", "compound_code": "RXR7+W8 Nizampur Khurd, Haryana, India"}, "vicinity": "Saidpur, Nizampur Khurd", "scope": "GOOGLE", "business_status": "OPERATIONAL", "types": ["doctor", "health", "point_of_interest", "establishment"], "icon": "https://maps.gstatic.com/mapfiles/place_api/icons/v1/png_71/generic_business-71.png"}]}