{"status": "OK", "html_attributions": [], "results": [{"rating": 5, "user_ratings_total": 3, "name": "Health Focus Center", "reference": "ChIJqdaM1AteUjoRFdpQbkoNKGI", "geometry": {"location": {"lat": 12.9698946, "lng": 80.1845798}, "viewport": {"northeast": {"lat": 12.9712467302915, "lng": 80.1859288802915}, "southwest": {"lat": 12.9685487697085, "lng": 80.18323091970849}}}, "opening_hours": {"open_now": true}, "place_id": "ChIJqdaM1AteUjoRFdpQbkoNKGI", "plus_code": {"global_code": "7M42X59M+XR", "compound_code": "X59M+XR Chennai, Tamil Nadu, India"}, "vicinity": "Jain Staff Colony Road, MMTC Colony, Nanganallur, Chennai", "photos": [{"photo_reference": "ATtYBwL8a37HkE1OKjnIALObK4zvfzpJrt9m0iF3bY4YK9IDbrrn3egvkQrEzn8cPIKMrQPiBecTIjWPjhHgE-POAMzbly7clncs3GvBS5n6Gik9nj2ahXITRmoa8TjNOh5WAkOj3TVDlisdHpxaAjg5bvxHtD7qqtbnqajyHsHyWCyOflS-", "width": 4048, "html_attributions": ["<a href=\"https://maps.google.com/maps/contrib/113031721469505412117\">prince bert</a>"], "height": 3036}], "scope": "GOOGLE", "business_status": "OPERATIONAL", "types": ["doctor", "health", "point_of_interest", "establishment"], "icon": "https://maps.gstatic.com/mapfiles/place_api/icons/v1/png_71/generic_business-71.png"}, {"name": "Interiors work", "reference": "ChIJu99XJJRdUjoREgmn6gTU7pQ", "geometry": {"location": {"lat": 12.9811503, "lng": 80.1913951}, "viewport": {"northeast": {"lat": 12.9825629802915, "lng": 80.1927545302915}, "southwest": {"lat": 12.9798650197085, "lng": 80.19005656970847}}}, "opening_hours": {"open_now": false}, "place_id": "ChIJu99XJJRdUjoREgmn6gTU7pQ", "plus_code": {"global_code": "7M42X5JR+FH", "compound_code": "X5JR+FH Chennai, Tamil Nadu, India"}, "vicinity": "MGR Street, Karunanidhi Nagar, Ullagaram, Nanganallur, Chennai", "scope": "GOOGLE", "business_status": "OPERATIONAL", "types": ["doctor", "health", "point_of_interest", "establishment"], "icon": "https://maps.gstatic.com/mapfiles/place_api/icons/v1/png_71/generic_business-71.png"}, {"rating": 5, "user_ratings_total": 1, "name": "Hicare Clinic ,SSB Sudarsan Apartment", "reference": "ChIJj7RRWFVnUjoRi_piePkYniY", "geometry": {"location": {"lat": 12.9880658, "lng": 80.1883413}, "viewport": {"northeast": {"lat": 12.9894280802915, "lng": 80.1896592302915}, "southwest": {"lat": 12.9867301197085, "lng": 80.18696126970849}}}, "opening_hours": {"open_now": false}, "place_id": "ChIJj7RRWFVnUjoRi_piePkYniY", "plus_code": {"global_code": "7M42X5QQ+68", "compound_code": "X5QQ+68 Chennai, Tamil Nadu, India"}, "vicinity": "New No. 1, SSB Sudarsan Apartment, Ground Floor, Bharathiyar, 2nd Street (South), Pazhavanthangal, Chennai", "photos": [{"photo_reference": "ATtYBwLT_jhreRc3YDw7rfN3OFQbEiARk6sR1bXRaLS9HPRIb4pS4pUVzwY-CQDh3m5wxqyNCSyntdsmOKotdKAHuJSi7ysPoGU98pRowT1VNPsitQ01IS-7be_WqUek32G8VPcxy3zAZZ6Sb0ntm8hhYCI1878-XtmdeVzLie-GIRxbbrzl", "width": 1080, "html_attributions": ["<a href=\"https://maps.google.com/maps/contrib/106379067900707694795\">Hariharan Kumar</a>"], "height": 608}], "scope": "GOOGLE", "business_status": "OPERATIONAL", "types": ["doctor", "health", "point_of_interest", "establishment"], "icon": "https://maps.gstatic.com/mapfiles/place_api/icons/v1/png_71/generic_business-71.png"}, {"rating": 5, "user_ratings_total": 1, "name": "Heal and feel clinic", "reference": "ChIJPVNvPKhfUjoRoVE9UV_QeNs", "geometry": {"location": {"lat": 12.9707212, "lng": 80.18711689999999}, "viewport": {"northeast": {"lat": 12.9721055802915, "lng": 80.1884770302915}, "southwest": {"lat": 12.9694076197085, "lng": 80.18577906970849}}}, "place_id": "ChIJPVNvPKhfUjoRoVE9UV_QeNs", "plus_code": {"global_code": "7M42X5CP+7R", "compound_code": "X5CP+7R Chennai, Tamil Nadu, India"}, "vicinity": "3rd Main Road, Nanganallur, Chennai", "scope": "GOOGLE", "business_status": "OPERATIONAL", "types": ["doctor", "health", "point_of_interest", "establishment"], "icon": "https://maps.gstatic.com/mapfiles/place_api/icons/v1/png_71/generic_business-71.png"}, {"name": "Santha Seelan R G (Dr)", "reference": "ChIJT55JO2pmUjoRbHAJxV8WDwU", "geometry": {"location": {"lat": 12.9847995, "lng": 80.19105429999999}, "viewport": {"northeast": {"lat": 12.9861478802915, "lng": 80.1924176802915}, "southwest": {"lat": 12.9834499197085, "lng": 80.18971971970849}}}, "place_id": "ChIJT55JO2pmUjoRbHAJxV8WDwU", "plus_code": {"global_code": "7M42X5MR+WC", "compound_code": "X5MR+WC Chennai, Tamil Nadu, India"}, "vicinity": "3rd Main Road, Nangnallur, Plot No 8/3, 8/2, Nangnallur, Nanganallur Co-op Society Colony, Nanganallur, Chennai", "scope": "GOOGLE", "business_status": "OPERATIONAL", "types": ["doctor", "health", "point_of_interest", "establishment"], "icon": "https://maps.gstatic.com/mapfiles/place_api/icons/v1/png_71/generic_business-71.png"}, {"name": "Shantha Bharathan Dr", "reference": "ChIJaeL2o_5dUjoRim366vQ_-Hw", "geometry": {"location": {"lat": 12.9827802, "lng": 80.1920253}, "viewport": {"northeast": {"lat": 12.9841268302915, "lng": 80.19339253029149}, "southwest": {"lat": 12.98142886970849, "lng": 80.19069456970848}}}, "place_id": "ChIJaeL2o_5dUjoRim366vQ_-Hw", "vicinity": "No 99, 1st Main Road Thilakar Avenue Balaiah Garden, Madipakkam, Madipakkam, Chennai", "scope": "GOOGLE", "business_status": "OPERATIONAL", "types": ["doctor", "health", "point_of_interest", "establishment"], "icon": "https://maps.gstatic.com/mapfiles/place_api/icons/v1/png_71/generic_business-71.png"}, {"rating": 4.6, "user_ratings_total": 38, "name": "RADIANT DENTAL CARE | Dental Clinic in Nanganallur | Invisalign Centre", "reference": "ChIJK2guaF5dUjoRDOgHtI0MExs", "geometry": {"location": {"lat": 12.9826996, "lng": 80.19218719999999}, "viewport": {"northeast": {"lat": 12.9840959802915, "lng": 80.1935401802915}, "southwest": {"lat": 12.9813980197085, "lng": 80.19084221970849}}}, "opening_hours": {"open_now": false}, "place_id": "ChIJK2guaF5dUjoRDOgHtI0MExs", "plus_code": {"global_code": "7M42X5MR+3V", "compound_code": "X5MR+3V Chennai, Tamil Nadu, India"}, "vicinity": "Hotel Saravana Square, Near grand sweets and restaurant, 1st Main Road, Nanganallur, Chennai", "photos": [{"photo_reference": "ATtYBwLTIouDx4O7fQUYlKbsfa3DDu_CyX1wywFdRQRVbULac_dqatjXcNPd3z5Pyfsw8XzZ5UvxJEnQXEXUwnohZU6ddE81bB7Nx0U6FUbIyLyWibuqV7Ptp6bs5OoV72f_jb7ZSK-46yGWkjud8hniFxWU2fH8HKnn53vjh_7aB-E9KTsl", "width": 1152, "html_attributions": ["<a href=\"https://maps.google.com/maps/contrib/108714943214701510418\">RADIANT DENTAL CARE | Dental Clinic in Nanganallur | Invisalign Centre</a>"], "height": 864}], "scope": "GOOGLE", "business_status": "OPERATIONAL", "types": ["doctor", "dentist", "health", "point_of_interest", "establishment"], "icon": "https://maps.gstatic.com/mapfiles/place_api/icons/v1/png_71/generic_business-71.png"}, {"rating": 5, "user_ratings_total": 1, "name": "Dr V Madhavan", "reference": "ChIJV4VMbf9dUjoRCRVira3czhQ", "geometry": {"location": {"lat": 12.9866091, "lng": 80.1910564}, "viewport": {"northeast": {"lat": 12.9880041802915, "lng": 80.1924086802915}, "southwest": {"lat": 12.9853062197085, "lng": 80.18971071970849}}}, "opening_hours": {"open_now": false}, "place_id": "ChIJV4VMbf9dUjoRCRVira3czhQ", "plus_code": {"global_code": "7M42X5PR+JC", "compound_code": "X5PR+JC Chennai, Tamil Nadu, India"}, "vicinity": "No.18 35th, 35, 1st Main Road, Ram Nagar, Nanganallur, Chennai", "scope": "GOOGLE", "business_status": "OPERATIONAL", "types": ["doctor", "health", "point_of_interest", "establishment"], "icon": "https://maps.gstatic.com/mapfiles/place_api/icons/v1/png_71/generic_business-71.png"}]}