{"status": "OK", "html_attributions": [], "results": [{"rating": 3.9, "user_ratings_total": 11, "permanently_closed": true, "name": "Asian Public School - CBSE School in Sohna Haryana", "reference": "ChIJHe12euslDTkR1kxkLKFTatY", "geometry": {"location": {"lat": 28.2646262, "lng": 77.1284438}, "viewport": {"northeast": {"lat": 28.2667118, "lng": 77.1296871802915}, "southwest": {"lat": 28.263931, "lng": 77.12698921970848}}}, "place_id": "ChIJHe12euslDTkR1kxkLKFTatY", "plus_code": {"global_code": "7JWV747H+V9", "compound_code": "747H+V9 Kharoda, Haryana, India"}, "vicinity": "Village Kharoda Dauhla, Harchandpur Road Sohna, Gurgaon, Haryana, Gurgaon", "scope": "GOOGLE", "business_status": "CLOSED_TEMPORARILY", "types": ["school", "point_of_interest", "establishment"], "icon": "https://maps.gstatic.com/mapfiles/place_api/icons/v1/png_71/school-71.png"}, {"rating": 4.7, "user_ratings_total": 3, "permanently_closed": true, "name": "Govt. Primary School, Harchandpur", "reference": "ChIJEUeGFzcmDTkRWT4B_h-rXbc", "geometry": {"location": {"lat": 28.2673478, "lng": 77.1391538}, "viewport": {"northeast": {"lat": 28.2685817802915, "lng": 77.1404234302915}, "southwest": {"lat": 28.2658838197085, "lng": 77.1377254697085}}}, "place_id": "ChIJEUeGFzcmDTkRWT4B_h-rXbc", "plus_code": {"global_code": "7JWV748Q+WM", "compound_code": "748Q+WM Harchandpur, Haryana, India"}, "vicinity": "Harchandpur", "photos": [{"photo_reference": "CmRaAAAAk8GYASKZyCVLAnnPPbVotlpewqwFpoDM-FoWKtIGG5O6fTEWlEFSlAdPxt72M5OF4GY4D_GJ5A_gnBnMCX5I0vJ9ZUAVq-Yn45CYv3E6jS2jNBzTNx90tSaG_EsZtnpfEhADg1LgHaHvTLCTTAzE01vdGhSyxR3v4G4Lln_mRQO1bWRL3JHRzQ", "width": 4000, "html_attributions": ["<a href=\"https://maps.google.com/maps/contrib/101463324563443073625\">Kumar</a>"], "height": 3000}], "scope": "GOOGLE", "business_status": "CLOSED_TEMPORARILY", "types": ["school", "point_of_interest", "establishment"], "icon": "https://maps.gstatic.com/mapfiles/place_api/icons/v1/png_71/school-71.png"}, {"rating": 5, "user_ratings_total": 3, "permanently_closed": true, "name": "Govt. Sr. Sec. School, Harchandpur (0765)", "reference": "ChIJ6WPlIDcmDTkRdZeLy2uu0xw", "geometry": {"location": {"lat": 28.2670323, "lng": 77.1397518}, "viewport": {"northeast": {"lat": 28.2683091302915, "lng": 77.1412582302915}, "southwest": {"lat": 28.2656111697085, "lng": 77.13856026970848}}}, "place_id": "ChIJ6WPlIDcmDTkRdZeLy2uu0xw", "plus_code": {"global_code": "7JWV748Q+RW", "compound_code": "748Q+RW Harchandpur, Haryana, India"}, "vicinity": "Harchandpur", "photos": [{"photo_reference": "CmRaAAAAD5fykbyYNF4-4nIm9NQYh6E-ahGN8IETECNFIJRSE-P4FiGr0L_zx_iVvg9lbYfnfGIZH-gMb6IscAcoN-8tFWkLv8t_GhHLLEdPKumFVEAHgBvWCwAlAglHR3dDZqjJEhDS2yUBKsrt2V_tojIHK0lKGhShqqa4gyNaIxhHW-PDx4_U-o906Q", "width": 1080, "html_attributions": ["<a href=\"https://maps.google.com/maps/contrib/109047013900239930749\">Deepak Bhamla</a>"], "height": 1920}], "scope": "GOOGLE", "business_status": "CLOSED_TEMPORARILY", "types": ["school", "point_of_interest", "establishment"], "icon": "https://maps.gstatic.com/mapfiles/place_api/icons/v1/png_71/school-71.png"}, {"rating": 4, "user_ratings_total": 2, "permanently_closed": true, "name": "Amar Jyoti Public School", "reference": "ChIJ_YnE4DkmDTkRYPe1evROHoA", "geometry": {"location": {"lat": 28.2668513, "lng": 77.13671529999999}, "viewport": {"northeast": {"lat": 28.2682900802915, "lng": 77.1380522802915}, "southwest": {"lat": 28.2655921197085, "lng": 77.13535431970848}}}, "place_id": "ChIJ_YnE4DkmDTkRYPe1evROHoA", "plus_code": {"global_code": "7JWV748P+PM", "compound_code": "748P+PM Harchandpur, Haryana, India"}, "vicinity": "ward no.1, ward no.1, Sohna Road, Harchandpur", "scope": "GOOGLE", "business_status": "CLOSED_TEMPORARILY", "types": ["school", "point_of_interest", "establishment"], "icon": "https://maps.gstatic.com/mapfiles/place_api/icons/v1/png_71/school-71.png"}, {"permanently_closed": true, "name": "Vedas international school nunhera", "reference": "ChIJSfRmKoYnDTkRlQGFDCDsbxE", "geometry": {"location": {"lat": 28.260343, "lng": 77.144381}, "viewport": {"northeast": {"lat": 28.2622151802915, "lng": 77.1462137302915}, "southwest": {"lat": 28.2595172197085, "lng": 77.1435157697085}}}, "place_id": "ChIJSfRmKoYnDTkRlQGFDCDsbxE", "plus_code": {"global_code": "7JWV746V+4Q", "compound_code": "746V+4Q Harchandpur, Haryana, India"}, "vicinity": "MDR 133", "scope": "GOOGLE", "business_status": "CLOSED_TEMPORARILY", "types": ["school", "point_of_interest", "establishment"], "icon": "https://maps.gstatic.com/mapfiles/place_api/icons/v1/png_71/school-71.png"}, {"rating": 4, "user_ratings_total": 38, "permanently_closed": true, "name": "Asian Public School - Best School in Sohna", "reference": "ChIJxYK_LjwmDTkRvWYqf4SzqwY", "geometry": {"location": {"lat": 28.2642738, "lng": 77.1285175}, "viewport": {"northeast": {"lat": 28.26689145, "lng": 77.12973393029151}, "southwest": {"lat": 28.26340125, "lng": 77.1270359697085}}}, "place_id": "ChIJxYK_LjwmDTkRvWYqf4SzqwY", "plus_code": {"global_code": "7JWV747H+PC", "compound_code": "747H+PC Sohna, Haryana, India"}, "vicinity": "Asian Public School Gurgaon Daulah, Harchandpur Road, Kharoda, Sohna", "photos": [{"photo_reference": "CmRaAAAA3ZsXhRtNTrPK6PVgbT3Ln5oT0JGvDvOI58oo-bL14isgY3o-0z6BRI9dR5WSy-YL5FCA-ArgAk-LKAy1taMZ_DpiuhucPsvL7qHDhgLJ4TGePC_eVKOYW6xpiAh2RlE-EhBR13lekC_cfccmA2db6XT9GhThniI4Uln-mZtyIajsUcElj-OaTg", "width": 1600, "html_attributions": ["<a href=\"https://maps.google.com/maps/contrib/118205228203542788454\">Asian Public School - Best School in Sohna</a>"], "height": 1068}], "scope": "GOOGLE", "business_status": "CLOSED_TEMPORARILY", "types": ["school", "point_of_interest", "establishment"], "icon": "https://maps.gstatic.com/mapfiles/place_api/icons/v1/png_71/school-71.png"}]}