{"status": "OK", "html_attributions": [], "results": [{"rating": 2.8, "user_ratings_total": 14, "name": "Axis Bank", "reference": "ChIJ5bEw6p0VrjsRzMcEu8iXAYc", "geometry": {"location": {"lat": 12.8968765, "lng": 77.6357235}, "viewport": {"northeast": {"lat": 12.8982389302915, "lng": 77.6370949302915}, "southwest": {"lat": 12.8955409697085, "lng": 77.63439696970849}}}, "opening_hours": {"open_now": true}, "place_id": "ChIJ5bEw6p0VrjsRzMcEu8iXAYc", "plus_code": {"global_code": "7J4VVJWP+Q7", "compound_code": "VJWP+Q7 Bengaluru, Karnataka, India"}, "vicinity": "No 5,9 & 10, 1st Flr, Sri Varaadi Towers, Hosur Road, Garvebhavi Palya, Bengaluru", "photos": [{"photo_reference": "ATtYBwKM-4ZulGhVpnTI_Oif0v5zmxO8LYTQeEzgR3nwG1dlhm50XipPkOmdw5wmG8sAso4rSPqJHNVtIwruCL47j2CQK4NSZ3x5U78p9DiellJFve5xTjdMx2mgsh9QNl4RjF6oFrBQMpEaZ_kYQ74U6HSSZ6b7OpfFsL4fo4tfVe62LFX7", "width": 2560, "html_attributions": ["<a href=\"https://maps.google.com/maps/contrib/102863506814931480300\">Vivek G</a>"], "height": 1920}], "scope": "GOOGLE", "business_status": "OPERATIONAL", "types": ["bank", "finance", "point_of_interest", "establishment"], "icon": "https://maps.gstatic.com/mapfiles/place_api/icons/v1/png_71/bank-71.png"}, {"rating": 3, "user_ratings_total": 59, "name": "HDFC Bank", "reference": "ChIJY3H-n40WrjsREiSrqTWNsac", "geometry": {"location": {"lat": 12.8981413, "lng": 77.6339205}, "viewport": {"northeast": {"lat": 12.8995213802915, "lng": 77.63532263029151}, "southwest": {"lat": 12.8968234197085, "lng": 77.63262466970849}}}, "opening_hours": {"open_now": true}, "place_id": "ChIJY3H-n40WrjsREiSrqTWNsac", "plus_code": {"global_code": "7J4VVJXM+7H", "compound_code": "VJXM+7H Bengaluru, Karnataka, India"}, "vicinity": "Site No 42 & 44, SD Cplx, Prabhava, Garvebhavipallya, Hosur Main Rd, Bengaluru", "photos": [{"photo_reference": "ATtYBwLzQLyXUkWK_INZUXGSO4pkP6YiYTmD41yXSDfPr3FAxf3SJqeK5xVfVFtBnSIZLSHRJcjkveH3V6yj8zVQRZ4jn2CO5tBjuQNxuAIWCMkOIQgjk4t_EFnNjVK2M9DDpxcdWmWdBRB0bkjnKeh4X_uiIRm4EVZ-3EEcAD0xdPjvIg73", "width": 3120, "html_attributions": ["<a href=\"https://maps.google.com/maps/contrib/109150766597806150862\">ram u</a>"], "height": 4160}], "scope": "GOOGLE", "business_status": "OPERATIONAL", "types": ["bank", "finance", "point_of_interest", "establishment"], "icon": "https://maps.gstatic.com/mapfiles/place_api/icons/v1/png_71/bank-71.png"}, {"name": "HDFC Bank ATM", "reference": "ChIJV0TqTiMVrjsROxdit1k6AuY", "geometry": {"location": {"lat": 12.8817618, "lng": 77.6260602}, "viewport": {"northeast": {"lat": 12.8831351802915, "lng": 77.6274090302915}, "southwest": {"lat": 12.8804372197085, "lng": 77.6247110697085}}}, "opening_hours": {"open_now": true}, "place_id": "ChIJV0TqTiMVrjsROxdit1k6AuY", "plus_code": {"global_code": "7J4VVJJG+PC", "compound_code": "VJJG+PC Bengaluru, Karnataka, India"}, "vicinity": "No 57, 1st Block Begur Rd, Akshayanagara - Begur Road, Vishwapriya Nagar, Bengaluru", "scope": "GOOGLE", "business_status": "OPERATIONAL", "types": ["atm", "bank", "finance", "point_of_interest", "establishment"], "icon": "https://maps.gstatic.com/mapfiles/place_api/icons/v1/png_71/atm-71.png"}, {"name": "ICICI BANK ATM", "reference": "ChIJRQBkhlAVrjsRK0nr3KlOIh4", "geometry": {"location": {"lat": 12.8945808, "lng": 77.6382065}, "viewport": {"northeast": {"lat": 12.8958824802915, "lng": 77.6395566802915}, "southwest": {"lat": 12.8931845197085, "lng": 77.6368587197085}}}, "opening_hours": {"open_now": true}, "place_id": "ChIJRQBkhlAVrjsRK0nr3KlOIh4", "plus_code": {"global_code": "7J4VVJVQ+R7", "compound_code": "VJVQ+R7 Bengaluru, Karnataka, India"}, "vicinity": "Medical Shop No 63, Munireddy Layout, Garvebhavi Palya, Bengaluru", "scope": "GOOGLE", "business_status": "OPERATIONAL", "types": ["bank", "finance", "point_of_interest", "establishment"], "icon": "https://maps.gstatic.com/mapfiles/place_api/icons/v1/png_71/bank-71.png"}, {"name": "HDFC Bank ATM", "reference": "ChIJBwYm4VMVrjsRPPPcwRL3-SY", "geometry": {"location": {"lat": 12.8892684, "lng": 77.63991}, "viewport": {"northeast": {"lat": 12.8906176802915, "lng": 77.64125943029151}, "southwest": {"lat": 12.8879197197085, "lng": 77.6385614697085}}}, "opening_hours": {"open_now": true}, "place_id": "ChIJBwYm4VMVrjsRPPPcwRL3-SY", "plus_code": {"global_code": "7J4VVJQQ+PX", "compound_code": "VJQQ+PX Bengaluru, Karnataka, India"}, "vicinity": "No 460, Bus Stop, near Kudlu, 5, Anekal Road, Kudlu, Bengaluru", "photos": [{"photo_reference": "ATtYBwK4BRILRmycIYvDcCgipsxRNl82CIb8pO0tL1Iy8I8JcJjGruhyD3Q3uSdl_RD4jJNrBp_woHLenTjxjqhpw8dP57EbdHWJ5iJY6GWmnACx9YbhH-U_4uPZpVy4-ObHY7mG_9MHIBqFKq-yXrOCw9kYGWpEHX7550sbgdNC7xmrlqB0", "width": 250, "html_attributions": ["<a href=\"https://maps.google.com/maps/contrib/115057005027077753450\">HDFC Bank ATM</a>"], "height": 250}], "scope": "GOOGLE", "business_status": "OPERATIONAL", "types": ["atm", "bank", "finance", "point_of_interest", "establishment"], "icon": "https://maps.gstatic.com/mapfiles/place_api/icons/v1/png_71/atm-71.png"}, {"rating": 4, "user_ratings_total": 1, "name": "HDFC Bank ATM", "reference": "ChIJBVep8M8UrjsR41m8BGDZtaY", "geometry": {"location": {"lat": 12.888947, "lng": 77.619981}, "viewport": {"northeast": {"lat": 12.8902938302915, "lng": 77.6213358802915}, "southwest": {"lat": 12.8875958697085, "lng": 77.61863791970849}}}, "opening_hours": {"open_now": true}, "place_id": "ChIJBVep8M8UrjsR41m8BGDZtaY", "plus_code": {"global_code": "7J4VVJQ9+HX", "compound_code": "VJQ9+HX Bengaluru, Karnataka, India"}, "vicinity": "HDFC Bank ATM, Devarachikkahalli, Bommanahalli, Bengaluru", "photos": [{"photo_reference": "ATtYBwKTo3ky9JjDIlQbunsikGtDzshJQ9J8KqzSTE48M2heIJkc6ZfI9LY1OJrSCr8W-f57mTIyfnGXRk31iW7JwY8sxrAZGdivYFMeL041CiHNPoJxZwzPRdgeNgjeU0WzimZlSME8dpv9l-kgMjSxd_VvppEqiwQEkC8CPULPQMqboPeN", "width": 1080, "html_attributions": ["<a href=\"https://maps.google.com/maps/contrib/116151604801889150333\">MANU ARJUN</a>"], "height": 1920}], "scope": "GOOGLE", "business_status": "OPERATIONAL", "types": ["atm", "bank", "finance", "point_of_interest", "establishment"], "icon": "https://maps.gstatic.com/mapfiles/place_api/icons/v1/png_71/atm-71.png"}, {"rating": 2.5, "user_ratings_total": 54, "name": "Canara Bank", "reference": "ChIJNyi9rusUrjsRKpYA61-50M4", "geometry": {"location": {"lat": 12.9001067, "lng": 77.6267962}, "viewport": {"northeast": {"lat": 12.9014403802915, "lng": 77.62820738029151}, "southwest": {"lat": 12.8987424197085, "lng": 77.6255094197085}}}, "opening_hours": {"open_now": true}, "place_id": "ChIJNyi9rusUrjsRKpYA61-50M4", "plus_code": {"global_code": "7J4VWJ2G+2P", "compound_code": "WJ2G+2P Bengaluru, Karnataka, India"}, "vicinity": "1&, 2, Begur Main Road, Bommanahalli, Bengaluru", "photos": [{"photo_reference": "ATtYBwJLsyNrmtCa_xcTaZEeNG3uy0CaQs1gb4K5Bc2uEal4uLq5fSmpZn74SzTjCpudUqJMFWn2j659By9wbSMxRPbKvzG_hXMKqek-BcIw7NSu0xZNmbV5TkE18t7Pj-YrI2BTYkhnYl_iu9LA_3nBHG82TxcwByDKy8Q9r95ZlZ2Yhk2y", "width": 4160, "html_attributions": ["<a href=\"https://maps.google.com/maps/contrib/107618144682105291182\">Uma Shankar Sharma</a>"], "height": 3120}], "scope": "GOOGLE", "business_status": "OPERATIONAL", "types": ["bank", "finance", "point_of_interest", "establishment"], "icon": "https://maps.gstatic.com/mapfiles/place_api/icons/v1/png_71/bank-71.png"}, {"name": "ICICI BANK ATM", "reference": "ChIJQ-9UQxkVrjsRVZ0p6m06zsQ", "geometry": {"location": {"lat": 12.886198, "lng": 77.6395493}, "viewport": {"northeast": {"lat": 12.8876038802915, "lng": 77.64090693029151}, "southwest": {"lat": 12.8849059197085, "lng": 77.6382089697085}}}, "opening_hours": {"open_now": true}, "place_id": "ChIJQ-9UQxkVrjsRVZ0p6m06zsQ", "plus_code": {"global_code": "7J4VVJPQ+FR", "compound_code": "VJPQ+FR Bengaluru, Karnataka, India"}, "vicinity": "51 2, Lakshmi Layout Main Road, Chikka Begur, Begur, Bengaluru", "scope": "GOOGLE", "business_status": "OPERATIONAL", "types": ["bank", "finance", "point_of_interest", "establishment"], "icon": "https://maps.gstatic.com/mapfiles/place_api/icons/v1/png_71/bank-71.png"}, {"name": "ICICI BANK ATM", "reference": "ChIJlaTlOBUVrjsR29v9em2a798", "geometry": {"location": {"lat": 12.8913231, "lng": 77.6196442}, "viewport": {"northeast": {"lat": 12.8927792302915, "lng": 77.6210123802915}, "southwest": {"lat": 12.8900812697085, "lng": 77.6183144197085}}}, "opening_hours": {"open_now": true}, "place_id": "ChIJlaTlOBUVrjsR29v9em2a798", "plus_code": {"global_code": "7J4VVJR9+GV", "compound_code": "VJR9+GV Bengaluru, Karnataka, India"}, "vicinity": "No-326, Dew, Nyanapahalli Main Road, Duo Heights Layout, Devarachikkana Halli, Bengaluru", "scope": "GOOGLE", "business_status": "OPERATIONAL", "types": ["bank", "finance", "point_of_interest", "establishment"], "icon": "https://maps.gstatic.com/mapfiles/place_api/icons/v1/png_71/bank-71.png"}, {"rating": 5, "user_ratings_total": 2, "name": "Mahalakshmi Enterprises. Money Transfer", "reference": "ChIJi09txcEUrjsRO69wXSKYjrg", "geometry": {"location": {"lat": 12.9001512, "lng": 77.6270435}, "viewport": {"northeast": {"lat": 12.9015121302915, "lng": 77.6283438302915}, "southwest": {"lat": 12.8988141697085, "lng": 77.62564586970849}}}, "opening_hours": {"open_now": true}, "place_id": "ChIJi09txcEUrjsRO69wXSKYjrg", "plus_code": {"global_code": "7J4VWJ2G+3R", "compound_code": "WJ2G+3R Bengaluru, Karnataka, India"}, "vicinity": "616, Begur Main Road, Hongasandra, Bengaluru", "scope": "GOOGLE", "business_status": "OPERATIONAL", "types": ["bank", "finance", "point_of_interest", "establishment"], "icon": "https://maps.gstatic.com/mapfiles/place_api/icons/v1/png_71/bank-71.png"}, {"name": "Finnex Business Service Pvt Ltd", "reference": "ChIJyzs9uboUrjsRJ5zHNxtNupM", "geometry": {"location": {"lat": 12.891521, "lng": 77.641166}, "viewport": {"northeast": {"lat": 12.8928092302915, "lng": 77.64239463029149}, "southwest": {"lat": 12.89011126970849, "lng": 77.63969666970848}}}, "opening_hours": {"open_now": true}, "place_id": "ChIJyzs9uboUrjsRJ5zHNxtNupM", "plus_code": {"global_code": "7J4VVJRR+JF", "compound_code": "VJRR+JF Bengaluru, Karnataka, India"}, "vicinity": "59/58, Kudlu Gate, Krishna Reddy Industrial Area, Hosapalaya, Muneshwara Nagar, Bengaluru", "scope": "GOOGLE", "business_status": "OPERATIONAL", "types": ["bank", "finance", "point_of_interest", "establishment"], "icon": "https://maps.gstatic.com/mapfiles/place_api/icons/v1/png_71/bank-71.png"}, {"name": "Axis Bank ATM", "reference": "ChIJRW6kCrMVrjsRfaGt2OdZPa8", "geometry": {"location": {"lat": 12.89776, "lng": 77.62095}, "viewport": {"northeast": {"lat": 12.8991429302915, "lng": 77.6223116802915}, "southwest": {"lat": 12.8964449697085, "lng": 77.61961371970848}}}, "opening_hours": {"open_now": true}, "place_id": "ChIJRW6kCrMVrjsRfaGt2OdZPa8", "plus_code": {"global_code": "7J4VVJXC+49", "compound_code": "VJXC+49 Bengaluru, Karnataka, India"}, "vicinity": "P No 30/3/1/1, Ground Floor, Kodichikkanahalli Main Road, Begur, Bengaluru", "scope": "GOOGLE", "business_status": "OPERATIONAL", "types": ["atm", "bank", "finance", "point_of_interest", "establishment"], "icon": "https://maps.gstatic.com/mapfiles/place_api/icons/v1/png_71/atm-71.png"}, {"rating": 2.6, "user_ratings_total": 7, "name": "Axis Bank", "reference": "ChIJ_ZRfzSkVrjsRjl35AobEVgY", "geometry": {"location": {"lat": 12.8978097, "lng": 77.6208876}, "viewport": {"northeast": {"lat": 12.8991726802915, "lng": 77.62224183029151}, "southwest": {"lat": 12.8964747197085, "lng": 77.6195438697085}}}, "opening_hours": {"open_now": true}, "place_id": "ChIJ_ZRfzSkVrjsRjl35AobEVgY", "plus_code": {"global_code": "7J4VVJXC+49", "compound_code": "VJXC+49 Bengaluru, Karnataka, India"}, "vicinity": "P No 30/3/1/1, Ground Floor, Kodichikkanahalli Main Road, Begur, Bengaluru", "scope": "GOOGLE", "business_status": "OPERATIONAL", "types": ["bank", "finance", "point_of_interest", "establishment"], "icon": "https://maps.gstatic.com/mapfiles/place_api/icons/v1/png_71/bank-71.png"}, {"rating": 5, "user_ratings_total": 8, "name": "SBI Officers' Prime Residency", "reference": "ChIJb46Eo_kVrjsRhc02qbUjvR4", "geometry": {"location": {"lat": 12.8962684, "lng": 77.6193674}, "viewport": {"northeast": {"lat": 12.8976479302915, "lng": 77.62056783029149}, "southwest": {"lat": 12.8949499697085, "lng": 77.61786986970849}}}, "place_id": "ChIJb46Eo_kVrjsRhc02qbUjvR4", "plus_code": {"global_code": "7J4VVJW9+GP", "compound_code": "VJW9+GP Bengaluru, Karnataka, India"}, "vicinity": "3rd Cross Road, Kodichikknahalli, Seenappa Layout, Bommanahalli, Bengaluru", "photos": [{"photo_reference": "ATtYBwIOcoglbiZPfC8P80LhH4yV9tEGIac_5M16dNUga2nfAscHIEO8HoZoYf_ImqgxfU-eZPUJAQjjIYBHA-lAemCnWL2pi65id7C6e5i_xWJ0aUd4dYaCOGQDx9HO4mRQ4jJZqMuOQNQRm6LFhNb0iKI3u0D3FejBS6smWWBt8LDNY5w", "width": 1229, "html_attributions": ["<a href=\"https://maps.google.com/maps/contrib/107760603943839175135\">Lohit Sontakki</a>"], "height": 1376}], "scope": "GOOGLE", "business_status": "OPERATIONAL", "types": ["bank", "finance", "point_of_interest", "establishment"], "icon": "https://maps.gstatic.com/mapfiles/place_api/icons/v1/png_71/bank-71.png"}, {"rating": 3, "user_ratings_total": 1, "name": "ICICI BANK ATM", "reference": "ChIJJwwT194VrjsR1GOMrRaSLGw", "geometry": {"location": {"lat": 12.8855448, "lng": 77.6416855}, "viewport": {"northeast": {"lat": 12.8869352302915, "lng": 77.6430242802915}, "southwest": {"lat": 12.8842372697085, "lng": 77.64032631970849}}}, "opening_hours": {"open_now": true}, "place_id": "ChIJJwwT194VrjsR1GOMrRaSLGw", "plus_code": {"global_code": "7J4VVJPR+6M", "compound_code": "VJPR+6M Bengaluru, Karnataka, India"}, "vicinity": "79, Hosur Road, Singasandra, Bengaluru", "scope": "GOOGLE", "business_status": "OPERATIONAL", "types": ["bank", "finance", "point_of_interest", "establishment"], "icon": "https://maps.gstatic.com/mapfiles/place_api/icons/v1/png_71/bank-71.png"}, {"rating": 5, "user_ratings_total": 3, "name": "Axis Bank", "reference": "ChIJAxeFQgcVrjsRxYzZ3a36-bQ", "geometry": {"location": {"lat": 12.88341, "lng": 77.64070199999999}, "viewport": {"northeast": {"lat": 12.8847526302915, "lng": 77.64201158029151}, "southwest": {"lat": 12.8820546697085, "lng": 77.6393136197085}}}, "opening_hours": {"open_now": true}, "place_id": "ChIJAxeFQgcVrjsRxYzZ3a36-bQ", "plus_code": {"global_code": "7J4VVJMR+97", "compound_code": "VJMR+97 Bengaluru, Karnataka, India"}, "vicinity": "176, Upper Ground Floor, AECS Layout Hosur Road, 2nd Main Road, B Block, Singasandra, Bengaluru", "photos": [{"photo_reference": "ATtYBwKdJYvxrdE1stgXZXCbpast5KWCv6WdxsD9Fl-Mjan4KQJJr5BC6mfjo0J__pkDSAhMU3J3r7g-8fO3cz0O_1kkPcITfpAWJqJbVf1TP3N0LtW9Zs-tk2LogkfW0jtqLtQI7bYQAzqhnORMkRp85dDz61qHg5BvHaSXlvG2Hac8rE3Z", "width": 1080, "html_attributions": ["<a href=\"https://maps.google.com/maps/contrib/112945106839507566219\">shubham tikekar</a>"], "height": 1920}], "scope": "GOOGLE", "business_status": "OPERATIONAL", "types": ["bank", "finance", "point_of_interest", "establishment"], "icon": "https://maps.gstatic.com/mapfiles/place_api/icons/v1/png_71/bank-71.png"}]}