{"status": "OK", "html_attributions": [], "results": [{"rating": 5, "user_ratings_total": 2, "name": "Karnataka Bank Hunasehalli Vagata Gp", "reference": "ChIJ1ZUcd8UOrjsRv5uNf0fnK5E", "geometry": {"location": {"lat": 13.009445, "lng": 77.8244172}, "viewport": {"northeast": {"lat": 13.0108453302915, "lng": 77.8257623302915}, "southwest": {"lat": 13.0081473697085, "lng": 77.82306436970849}}}, "place_id": "ChIJ1ZUcd8UOrjsRv5uNf0fnK5E", "plus_code": {"global_code": "7J5V2R5F+QQ", "compound_code": "2R5F+QQ Hunasahally, Karnataka, India"}, "vicinity": "shop no 4 & 5 jadigenahalli hobli, Hunasahally", "photos": [{"photo_reference": "ATtYBwLKHVKfJFqIqAV7OpafDBF1Zs-VVFf2zZhd1oCYFIuIlzHewkNCrzZ7b4W1QoQLfKh4cMKAufnuetr9giwg3N5t8t8CByn2WOMjMveD9Cz_zRiGWf8oOKMTuwC-V-MC1OsQKGRIaY7_N6cn6EdB6_Jwo0L_Lm8WYsknisDigYtBdI-u", "width": 640, "html_attributions": ["<a href=\"https://maps.google.com/maps/contrib/115458378260200547483\">Divakar gowda Gowda</a>"], "height": 640}], "scope": "GOOGLE", "business_status": "OPERATIONAL", "types": ["bank", "finance", "point_of_interest", "establishment"], "icon": "https://maps.gstatic.com/mapfiles/place_api/icons/v1/png_71/bank-71.png"}, {"name": "Srriyan Enterpriises", "reference": "ChIJh1ehB8UOrjsR8fHGiqj2qQY", "geometry": {"location": {"lat": 13.0092946, "lng": 77.82296550000001}, "viewport": {"northeast": {"lat": 13.0107162302915, "lng": 77.8243087302915}, "southwest": {"lat": 13.0080182697085, "lng": 77.8216107697085}}}, "opening_hours": {"open_now": true}, "place_id": "ChIJh1ehB8UOrjsR8fHGiqj2qQY", "plus_code": {"global_code": "7J5V2R5F+P5", "compound_code": "2R5F+P5 Hunasahally, Karnataka, India"}, "vicinity": "Hunasahally", "photos": [{"photo_reference": "ATtYBwI4AV654X3vfDBe86wIXbohfWxyZf_No4EhgNfZu1KcbRd7SzhEVKcTsEFhLAbBcL6X9pcj1GbT7obf6rz5cJIdnokUXyJuRNiLlqoqK-mdMWlA-TrFukixK5vDLNEi6IJ2xgWRolYqJlEreutVfRlPxrpE06PPNqT1Bl46oZbmpUqZ", "width": 3456, "html_attributions": ["<a href=\"https://maps.google.com/maps/contrib/116524739750951111475\">Santhosh Abhi</a>"], "height": 4608}], "scope": "GOOGLE", "business_status": "OPERATIONAL", "types": ["bank", "finance", "point_of_interest", "establishment"], "icon": "https://maps.gstatic.com/mapfiles/place_api/icons/v1/png_71/bank-71.png"}]}