{"status": "OK", "html_attributions": [], "results": [{"rating": 5, "user_ratings_total": 1, "permanently_closed": true, "name": "Garibdas Public School", "reference": "ChIJsZBi1c8LDTkRNcNJFkZ_1E8", "geometry": {"location": {"lat": 28.689077, "lng": 76.8585853}, "viewport": {"northeast": {"lat": 28.6904331802915, "lng": 76.8598739302915}, "southwest": {"lat": 28.6877352197085, "lng": 76.85717596970849}}}, "place_id": "ChIJsZBi1c8LDTkRNcNJFkZ_1E8", "plus_code": {"global_code": "7JWRMVQ5+JC", "compound_code": "MVQ5+JC Tandaheri, Haryana, India"}, "vicinity": "Tandaheri", "photos": [{"photo_reference": "ATtYBwIacmfMJBo5E7voDuxgMpI6GuLLmmV6bVMTj0a0DQK4XKZwrCufAoWcIxLonjGiC5jz8sSGhLnIbvITdgKUl2HkyeCrZcKBW7ZzeukwIkHdB_wfPb3xgmOCJOqJjOju9ysmERxpNAJI5WyLvgdzzVGhMGpYgrbN0nyud2EskJjlF2YY", "width": 1032, "html_attributions": ["<a href=\"https://maps.google.com/maps/contrib/107832773954835293188\">sanjay kumar</a>"], "height": 774}], "scope": "GOOGLE", "business_status": "CLOSED_TEMPORARILY", "types": ["school", "point_of_interest", "establishment"], "icon": "https://maps.gstatic.com/mapfiles/place_api/icons/v1/png_71/school-71.png"}, {"permanently_closed": true, "name": "Read India", "reference": "ChIJ7WfNI9gLDTkRRZWhuyU4z3o", "geometry": {"location": {"lat": 28.6907475, "lng": 76.8555535}, "viewport": {"northeast": {"lat": 28.6920776302915, "lng": 76.8569454802915}, "southwest": {"lat": 28.6893796697085, "lng": 76.8542475197085}}}, "place_id": "ChIJ7WfNI9gLDTkRRZWhuyU4z3o", "plus_code": {"global_code": "7JWRMVR4+76", "compound_code": "MVR4+76 Tandaheri, Haryana, India"}, "vicinity": "Tandaheri", "scope": "GOOGLE", "business_status": "CLOSED_TEMPORARILY", "types": ["school", "point_of_interest", "establishment"], "icon": "https://maps.gstatic.com/mapfiles/place_api/icons/v1/png_71/school-71.png"}, {"rating": 5, "user_ratings_total": 4, "permanently_closed": true, "name": "\u0936\u094d\u0930\u0940 \u0938\u091a\u094d\u091a\u093e \u0935\u0948\u0926\u093f\u0915 \u0938\u0902\u0938\u094d\u0915\u0943\u0924 \u092e\u0939\u093e\u0935\u093f\u0926\u094d\u092f\u093e\u0932\u092f", "reference": "ChIJCfzEUqcLDTkRtIvK2l2PaJM", "geometry": {"location": {"lat": 28.6883439, "lng": 76.8649015}, "viewport": {"northeast": {"lat": 28.6898804802915, "lng": 76.8662739302915}, "southwest": {"lat": 28.6871825197085, "lng": 76.86357596970849}}}, "place_id": "ChIJCfzEUqcLDTkRtIvK2l2PaJM", "plus_code": {"global_code": "7JWRMVQ7+8X", "compound_code": "MVQ7+8X Kherka Musalman, Haryana, India"}, "vicinity": "", "photos": [{"photo_reference": "ATtYBwKreXVnDP4yewtYh_sUaZt26XGd-xUE6q-DT3K8D3T6XHfALZcOQqpR1uS362NzU7QqfqWbHwrQue6pJRhLH7ec7dcHaR8Ezj7ZRhiVGmc-fG63a6fj-VXigPeUXkv4zC22aIY-L8ePk7w53EjPihw5gQ7BvcifynWOkWKh7fmMmarj", "width": 4096, "html_attributions": ["<a href=\"https://maps.google.com/maps/contrib/103204748509397567327\">\u0905\u092d\u093f\u0937\u0947\u0915: \u092a\u0930\u0917\u093e\u0901\u0908</a>"], "height": 2304}], "scope": "GOOGLE", "business_status": "CLOSED_TEMPORARILY", "types": ["school", "point_of_interest", "establishment"], "icon": "https://maps.gstatic.com/mapfiles/place_api/icons/v1/png_71/school-71.png"}, {"rating": 3.8, "user_ratings_total": 4, "permanently_closed": true, "name": "Government School", "reference": "ChIJbW7DC2YLDTkRxxraPl_gnDY", "geometry": {"location": {"lat": 28.690279, "lng": 76.85464429999999}, "viewport": {"northeast": {"lat": 28.6919431302915, "lng": 76.8561770802915}, "southwest": {"lat": 28.6892451697085, "lng": 76.8534791197085}}}, "place_id": "ChIJbW7DC2YLDTkRxxraPl_gnDY", "plus_code": {"global_code": "7JWRMVR3+4V", "compound_code": "MVR3+4V Tandaheri, Haryana, India"}, "vicinity": "teh.-bahadurgarh, distt. - jhajjar, Major District Road 122, Tandaheri", "scope": "GOOGLE", "business_status": "CLOSED_TEMPORARILY", "types": ["school", "point_of_interest", "establishment"], "icon": "https://maps.gstatic.com/mapfiles/place_api/icons/v1/png_71/school-71.png"}, {"permanently_closed": true, "name": "Govt School Ground", "reference": "ChIJtd4samYLDTkRn6aY9oyFcZ0", "geometry": {"location": {"lat": 28.6895068, "lng": 76.8535334}, "viewport": {"northeast": {"lat": 28.6909773802915, "lng": 76.85471538029151}, "southwest": {"lat": 28.6882794197085, "lng": 76.8520174197085}}}, "place_id": "ChIJtd4samYLDTkRn6aY9oyFcZ0", "plus_code": {"global_code": "7JWRMVQ3+RC", "compound_code": "MVQ3+RC Tandaheri, Haryana, India"}, "vicinity": "Tandaheri", "scope": "GOOGLE", "business_status": "CLOSED_TEMPORARILY", "types": ["school", "point_of_interest", "establishment"], "icon": "https://maps.gstatic.com/mapfiles/place_api/icons/v1/png_71/school-71.png"}, {"rating": 4, "user_ratings_total": 1, "permanently_closed": true, "name": "Govt.School Ground , Tanda Heri", "reference": "ChIJt8UramYLDTkRqRtj0Q4oqF8", "geometry": {"location": {"lat": 28.68948739999999, "lng": 76.85351899999999}, "viewport": {"northeast": {"lat": 28.6909588302915, "lng": 76.8546997802915}, "southwest": {"lat": 28.6882608697085, "lng": 76.85200181970848}}}, "place_id": "ChIJt8UramYLDTkRqRtj0Q4oqF8", "plus_code": {"global_code": "7JWRMVQ3+QC", "compound_code": "MVQ3+QC Tandaheri, Haryana, India"}, "vicinity": "Tandaheri", "scope": "GOOGLE", "business_status": "CLOSED_TEMPORARILY", "types": ["school", "point_of_interest", "establishment"], "icon": "https://maps.gstatic.com/mapfiles/place_api/icons/v1/png_71/school-71.png"}, {"permanently_closed": true, "name": "Mahila Bal Vikas Kendra", "reference": "ChIJw-5Nq6sLDTkR1eji584U3AM", "geometry": {"location": {"lat": 28.68251489999999, "lng": 76.8519159}, "viewport": {"northeast": {"lat": 28.6850655, "lng": 76.8579291}, "southwest": {"lat": 28.6816647, "lng": 76.84991149999999}}}, "place_id": "ChIJw-5Nq6sLDTkR1eji584U3AM", "plus_code": {"global_code": "7JWRMVM2+2Q", "compound_code": "MVM2+2Q Daboda Kalan, Haryana, India"}, "vicinity": "Daboda Kalan", "scope": "GOOGLE", "business_status": "CLOSED_TEMPORARILY", "types": ["school", "point_of_interest", "establishment"], "icon": "https://maps.gstatic.com/mapfiles/place_api/icons/v1/png_71/school-71.png"}, {"permanently_closed": true, "name": "GMS Dabodha Kalan", "reference": "ChIJVVVVVWALDTkRo5m-a9pyGHo", "geometry": {"location": {"lat": 28.68251489999999, "lng": 76.8519159}, "viewport": {"northeast": {"lat": 28.6850655, "lng": 76.8579291}, "southwest": {"lat": 28.6816647, "lng": 76.84991149999999}}}, "place_id": "ChIJVVVVVWALDTkRo5m-a9pyGHo", "plus_code": {"global_code": "7JWRMVM2+2Q", "compound_code": "MVM2+2Q Daboda Kalan, Haryana, India"}, "vicinity": "Daboda Kalan", "scope": "GOOGLE", "business_status": "CLOSED_TEMPORARILY", "types": ["school", "point_of_interest", "establishment"], "icon": "https://maps.gstatic.com/mapfiles/place_api/icons/v1/png_71/school-71.png"}, {"permanently_closed": true, "name": "animal Hospital Mahandipur", "reference": "ChIJw085bccLDTkR1QBFHo9W3mE", "geometry": {"location": {"lat": 28.6823804, "lng": 76.8518708}, "viewport": {"northeast": {"lat": 28.68513274999999, "lng": 76.85795165}, "southwest": {"lat": 28.68146294999999, "lng": 76.84984385}}}, "place_id": "ChIJw085bccLDTkR1QBFHo9W3mE", "plus_code": {"global_code": "7JWRMVJ2+XP", "compound_code": "MVJ2+XP Daboda Kalan, Haryana, India"}, "vicinity": "Daboda Kalan", "scope": "GOOGLE", "business_status": "CLOSED_TEMPORARILY", "types": ["school", "point_of_interest", "establishment"], "icon": "https://maps.gstatic.com/mapfiles/place_api/icons/v1/png_71/school-71.png"}]}