{"status": "OK", "html_attributions": [], "results": [{"name": "Govt school site", "reference": "ChIJf5FuAQ8HDTkRkFfnsWtd4SA", "geometry": {"location": {"lat": 28.7729626, "lng": 77.0770529}, "viewport": {"northeast": {"lat": 28.7742898302915, "lng": 77.07834498029152}, "southwest": {"lat": 28.7715918697085, "lng": 77.0756470197085}}}, "place_id": "ChIJf5FuAQ8HDTkRkFfnsWtd4SA", "plus_code": {"global_code": "7JWVQ3FG+5R", "compound_code": "Q3FG+5R Delhi, India"}, "vicinity": "Sector 34, Khera Khurd, Delhi", "scope": "GOOGLE", "business_status": "OPERATIONAL", "types": ["school", "point_of_interest", "establishment"], "icon": "https://maps.gstatic.com/mapfiles/place_api/icons/v1/png_71/school-71.png"}, {"rating": 5, "user_ratings_total": 7, "name": "Kiddiez Play School Rohini", "reference": "ChIJa1QEUJ0HDTkRezFYBBO9zLo", "geometry": {"location": {"lat": 28.7684667, "lng": 77.0721908}, "viewport": {"northeast": {"lat": 28.7698080302915, "lng": 77.0735358802915}, "southwest": {"lat": 28.7671100697085, "lng": 77.0708379197085}}}, "opening_hours": {"open_now": false}, "place_id": "ChIJa1QEUJ0HDTkRezFYBBO9zLo", "plus_code": {"global_code": "7JWVQ39C+9V", "compound_code": "Q39C+9V Delhi, India"}, "vicinity": "Pocket 3, Sector 34, Rohini, Delhi", "scope": "GOOGLE", "business_status": "OPERATIONAL", "types": ["school", "point_of_interest", "establishment"], "icon": "https://maps.gstatic.com/mapfiles/place_api/icons/v1/png_71/school-71.png"}, {"rating": 5, "user_ratings_total": 1, "permanently_closed": true, "name": "Nature School of Learning", "reference": "ChIJrQFhzToHDTkR7CSy014-Ss4", "geometry": {"location": {"lat": 28.7677044, "lng": 77.09225030000002}, "viewport": {"northeast": {"lat": 28.7691112302915, "lng": 77.09347168029151}, "southwest": {"lat": 28.7664132697085, "lng": 77.0907737197085}}}, "place_id": "ChIJrQFhzToHDTkR7CSy014-Ss4", "plus_code": {"global_code": "7JWVQ39R+3W", "compound_code": "Q39R+3W Delhi, India"}, "vicinity": "Sector 29, Rohini, Delhi", "scope": "GOOGLE", "business_status": "CLOSED_TEMPORARILY", "types": ["school", "point_of_interest", "establishment"], "icon": "https://maps.gstatic.com/mapfiles/place_api/icons/v1/png_71/school-71.png"}, {"permanently_closed": true, "name": "Aggarwal's play school", "reference": "ChIJAQCwIDsHDTkRwGVSVvGboFY", "geometry": {"location": {"lat": 28.761072, "lng": 77.0880584}, "viewport": {"northeast": {"lat": 28.7624410802915, "lng": 77.08936518029151}, "southwest": {"lat": 28.7597431197085, "lng": 77.0866672197085}}}, "place_id": "ChIJAQCwIDsHDTkRwGVSVvGboFY", "plus_code": {"global_code": "7JWVQ36Q+C6", "compound_code": "Q36Q+C6 Delhi, India"}, "vicinity": "Flat no.15, Third Floor, LIG DDA Flats, Block F9, Sector 34, Rohini, Delhi", "scope": "GOOGLE", "business_status": "CLOSED_TEMPORARILY", "types": ["school", "point_of_interest", "establishment"], "icon": "https://maps.gstatic.com/mapfiles/place_api/icons/v1/png_71/school-71.png"}, {"rating": 5, "user_ratings_total": 14, "name": "Cannyway Pre-School", "reference": "ChIJuZnUP60HDTkRM0_fo96wSDk", "geometry": {"location": {"lat": 28.7646707, "lng": 77.0924196}, "viewport": {"northeast": {"lat": 28.7660707302915, "lng": 77.0938505302915}, "southwest": {"lat": 28.7633727697085, "lng": 77.0911525697085}}}, "opening_hours": {"open_now": false}, "place_id": "ChIJuZnUP60HDTkRM0_fo96wSDk", "plus_code": {"global_code": "7JWVQ37R+VX", "compound_code": "Q37R+VX Delhi, India"}, "vicinity": "Flat 903,Block-C,Gh-1,Creative Heights, Sector 29, Rohini, Delhi", "photos": [{"photo_reference": "ATtYBwJojwUe6zzqsryb2rWVqcg3ZNo1W8uqwVW3vJgydnO5ZeAa4Hb2v8wPISObNhIQ5z6l19axgWyz38YejvvdSXtCKrJM3tkqXyAsyrIZrJV6jsNbHjWpGv-bc4-zSdBL0OlwaqzqfFwjzqPabjqCDTI0vrm_TgcgYUqiu3zpR4q0MGA", "width": 5456, "html_attributions": ["<a href=\"https://maps.google.com/maps/contrib/112618198327742332909\">Cannyway Pre-School</a>"], "height": 3064}], "scope": "GOOGLE", "business_status": "OPERATIONAL", "types": ["school", "point_of_interest", "establishment"], "icon": "https://maps.gstatic.com/mapfiles/place_api/icons/v1/png_71/school-71.png"}, {"name": "CANNYWAY PRE SCHOOL", "reference": "ChIJVVVVlTAHDTkRB8Hs4Q9Youo", "geometry": {"location": {"lat": 28.7646707, "lng": 77.0924196}, "viewport": {"northeast": {"lat": 28.7660196802915, "lng": 77.09376858029151}, "southwest": {"lat": 28.7633217197085, "lng": 77.09107061970849}}}, "place_id": "ChIJVVVVlTAHDTkRB8Hs4Q9Youo", "vicinity": "Creative Heights, 903, Block C, Sector 29, Rohini, Delhi", "scope": "GOOGLE", "business_status": "OPERATIONAL", "types": ["school", "point_of_interest", "establishment"], "icon": "https://maps.gstatic.com/mapfiles/place_api/icons/v1/png_71/school-71.png"}]}