{"status": "OK", "html_attributions": [], "results": [{"rating": 5, "user_ratings_total": 1, "name": "V.p Industrial Suppliers", "reference": "ChIJy-JX_A8VrjsRMYXXLHVFN68", "geometry": {"location": {"lat": 12.9649828, "lng": 77.58032229999999}, "viewport": {"northeast": {"lat": 12.9662886302915, "lng": 77.5816638802915}, "southwest": {"lat": 12.9635906697085, "lng": 77.5789659197085}}}, "place_id": "ChIJy-JX_A8VrjsRMYXXLHVFN68", "plus_code": {"global_code": "7J4VXH7J+X4", "compound_code": "XH7J+X4 Bengaluru, Karnataka, India"}, "vicinity": "Belagodu Complex, #40/3, 1st Floor, Dr, Sadar Patrappa Road, Bengaluru", "photos": [{"photo_reference": "ATtYBwI6LPMsmzSs3gk-sYdRUFyTWa6QXJkc6gGHAvR5qRoiz_HsIhRR0AofcyQyAUcEvtw7EXR_-w2pzz1h5Ra7N3XgEgNW1BKgzsY7P77LofbGrcweZjuRTP0hmjUPUNrL8W9PjECV2zutcRv7B5n6bqncvO-9cPw4UDA5FQCsQ8s6AsPs", "width": 2656, "html_attributions": ["<a href=\"https://maps.google.com/maps/contrib/109684508138831602237\">Support Direct India Pvt Ltd</a>"], "height": 3984}], "scope": "GOOGLE", "business_status": "OPERATIONAL", "types": ["supermarket", "grocery_or_supermarket", "food", "point_of_interest", "store", "establishment"], "icon": "https://maps.gstatic.com/mapfiles/place_api/icons/v1/png_71/shopping-71.png"}, {"rating": 5, "user_ratings_total": 1, "name": "R Super Mart", "reference": "ChIJTYl8--EVrjsR2Rz9HDfUGAk", "geometry": {"location": {"lat": 12.9661049, "lng": 77.579708}, "viewport": {"northeast": {"lat": 12.9674489802915, "lng": 77.58107478029149}, "southwest": {"lat": 12.9647510197085, "lng": 77.57837681970848}}}, "opening_hours": {"open_now": true}, "place_id": "ChIJTYl8--EVrjsR2Rz9HDfUGAk", "plus_code": {"global_code": "7J4VXH8H+CV", "compound_code": "XH8H+CV Bengaluru, Karnataka, India"}, "vicinity": "Dodpete, Nagarathpete, Bengaluru", "scope": "GOOGLE", "business_status": "OPERATIONAL", "types": ["supermarket", "grocery_or_supermarket", "food", "point_of_interest", "store", "establishment"], "icon": "https://maps.gstatic.com/mapfiles/place_api/icons/v1/png_71/shopping-71.png"}, {"rating": 5, "user_ratings_total": 1, "name": "KULDEEP FABRICS", "reference": "ChIJmww-rEYXrjsROe3im-LJxoU", "geometry": {"location": {"lat": 12.9685557, "lng": 77.5790243}, "viewport": {"northeast": {"lat": 12.9699070302915, "lng": 77.5803686802915}, "southwest": {"lat": 12.9672090697085, "lng": 77.5776707197085}}}, "opening_hours": {"open_now": true}, "place_id": "ChIJmww-rEYXrjsROe3im-LJxoU", "plus_code": {"global_code": "7J4VXH9H+CJ", "compound_code": "XH9H+CJ Bengaluru, Karnataka, India"}, "vicinity": "NEAR, CANERA BANK, VENKTESHWARA MARKET AVENU ROAD, Avenue Road, Bengaluru", "scope": "GOOGLE", "business_status": "OPERATIONAL", "types": ["supermarket", "grocery_or_supermarket", "food", "point_of_interest", "store", "establishment"], "icon": "https://maps.gstatic.com/mapfiles/place_api/icons/v1/png_71/shopping-71.png"}, {"rating": 5, "user_ratings_total": 1, "name": "Fance Store", "reference": "ChIJU1Bb8AkWrjsRJFHMtejW32I", "geometry": {"location": {"lat": 12.9672444, "lng": 77.57854600000002}, "viewport": {"northeast": {"lat": 12.9686477302915, "lng": 77.57978033029151}, "southwest": {"lat": 12.9659497697085, "lng": 77.5770823697085}}}, "place_id": "ChIJU1Bb8AkWrjsRJFHMtejW32I", "plus_code": {"global_code": "7J4VXH8H+VC", "compound_code": "XH8H+VC Bengaluru, Karnataka, India"}, "vicinity": "Avenue Road, Dodpete, Chickpet, Bengaluru", "scope": "GOOGLE", "business_status": "OPERATIONAL", "types": ["supermarket", "grocery_or_supermarket", "food", "point_of_interest", "store", "establishment"], "icon": "https://maps.gstatic.com/mapfiles/place_api/icons/v1/png_71/shopping-71.png"}, {"name": "Shree Mataji Traders", "reference": "ChIJSQAwAeIVrjsRkY2CxOqh6NM", "geometry": {"location": {"lat": 12.9662124, "lng": 77.5788218}, "viewport": {"northeast": {"lat": 12.9675955802915, "lng": 77.5801838302915}, "southwest": {"lat": 12.9648976197085, "lng": 77.5774858697085}}}, "place_id": "ChIJSQAwAeIVrjsRkY2CxOqh6NM", "plus_code": {"global_code": "7J4VXH8H+FG", "compound_code": "XH8H+FG Bengaluru, Karnataka, India"}, "vicinity": "210, Kumbarpet Main Road, Dodpete, Nagarathpete, Bengaluru", "scope": "GOOGLE", "business_status": "OPERATIONAL", "types": ["supermarket", "grocery_or_supermarket", "food", "point_of_interest", "store", "establishment"], "icon": "https://maps.gstatic.com/mapfiles/place_api/icons/v1/png_71/shopping-71.png"}, {"rating": 5, "user_ratings_total": 1, "name": "P Nagakumar", "reference": "ChIJGXVkqo4XrjsR4souFMrn6vA", "geometry": {"location": {"lat": 12.9673045, "lng": 77.57841479999999}, "viewport": {"northeast": {"lat": 12.9686480802915, "lng": 77.57976088029152}, "southwest": {"lat": 12.9659501197085, "lng": 77.5770629197085}}}, "place_id": "ChIJGXVkqo4XrjsR4souFMrn6vA", "plus_code": {"global_code": "7J4VXH8H+W9", "compound_code": "XH8H+W9 Bengaluru, Karnataka, India"}, "vicinity": "39, Mamulpet Rd, Dodpete, Nagarathpete, Bengaluru", "photos": [{"photo_reference": "ATtYBwJqqKOUEKj7G_S5SqRqL3ls4x1iMOS2g-SCwokftbzudKYOtDtlY1SB4sE9NKPl0WwkCwBV9dAs74TOShS62nNhl5naFM6wU0UvIGY3s4z2Wx6eSoKKUokugG8FjYNKkryw7TQUsBVBELj8v0_XpCApgc3c3uTQFHBDX7byN6fIyyzF", "width": 4000, "html_attributions": ["<a href=\"https://maps.google.com/maps/contrib/118028586426904100940\">Adithya Nanjunda</a>"], "height": 3000}], "scope": "GOOGLE", "business_status": "OPERATIONAL", "types": ["supermarket", "grocery_or_supermarket", "food", "point_of_interest", "store", "establishment"], "icon": "https://maps.gstatic.com/mapfiles/place_api/icons/v1/png_71/shopping-71.png"}, {"rating": 3.3, "user_ratings_total": 7, "name": "Bluepay Ventures Pvt Ltd", "reference": "ChIJxXhqrHgWrjsRfVJu8zWIH8g", "geometry": {"location": {"lat": 12.9679802, "lng": 77.6018012}, "viewport": {"northeast": {"lat": 12.9692962802915, "lng": 77.6030775802915}, "southwest": {"lat": 12.9665983197085, "lng": 77.60037961970849}}}, "opening_hours": {"open_now": true}, "place_id": "ChIJxXhqrHgWrjsRfVJu8zWIH8g", "plus_code": {"global_code": "7J4VXJ92+5P", "compound_code": "XJ92+5P Bengaluru, Karnataka, India"}, "vicinity": "unit #107, 1st floor, Prestige Towers, Residency Road, Richmond Town, Bengaluru", "scope": "GOOGLE", "business_status": "OPERATIONAL", "types": ["supermarket", "grocery_or_supermarket", "food", "point_of_interest", "store", "establishment"], "icon": "https://maps.gstatic.com/mapfiles/place_api/icons/v1/png_71/shopping-71.png"}, {"rating": 4.4, "user_ratings_total": 9, "name": "Onkar Bearing Co.", "reference": "ChIJHXFTet0VrjsR5YqOe6De94s", "geometry": {"location": {"lat": 12.9589457, "lng": 77.5854943}, "viewport": {"northeast": {"lat": 12.9602870802915, "lng": 77.58686858029151}, "southwest": {"lat": 12.9575891197085, "lng": 77.58417061970849}}}, "opening_hours": {"open_now": true}, "place_id": "ChIJHXFTet0VrjsR5YqOe6De94s", "plus_code": {"global_code": "7J4VXH5P+H5", "compound_code": "XH5P+H5 Bengaluru, Karnataka, India"}, "vicinity": "1st Floor, 1st B Cross SGN Layout Cosmic Embassy No.10, Bengaluru", "photos": [{"photo_reference": "ATtYBwLJmUS38Nmg1cy7MDHSUFeYboKpm9wxjkqO9kwIgITfAubYDVrZt8iblXEjRn-lssKo6DFczuuNfAydFXNFLGV6ZHG4NQ-14XwpJPM959DCG8SX1lEtaqF4CmnMZUkHcuqzRnv2oPPsu-CiW-g6hFYgOw_q8FYYQewuO64pcB3LcXZ4", "width": 3024, "html_attributions": ["<a href=\"https://maps.google.com/maps/contrib/108065172901290126627\">Gaurav Jaiswal</a>"], "height": 4032}], "scope": "GOOGLE", "business_status": "OPERATIONAL", "types": ["supermarket", "grocery_or_supermarket", "food", "point_of_interest", "store", "establishment"], "icon": "https://maps.gstatic.com/mapfiles/place_api/icons/v1/png_71/shopping-71.png"}, {"rating": 5, "user_ratings_total": 1, "name": "Kr Market", "reference": "ChIJlQkQR14VrjsRUk8fCpHpF9M", "geometry": {"location": {"lat": 12.9625646, "lng": 77.5800649}, "viewport": {"northeast": {"lat": 12.9639179302915, "lng": 77.58141443029149}, "southwest": {"lat": 12.9612199697085, "lng": 77.57871646970848}}}, "place_id": "ChIJlQkQR14VrjsRUk8fCpHpF9M", "plus_code": {"global_code": "7J4VXH7J+22", "compound_code": "XH7J+22 Bengaluru, Karnataka, India"}, "vicinity": "New Bamboo Bazaar Road, Kalasipalyam New Extension, Kalasipalya, Bengaluru", "scope": "GOOGLE", "business_status": "OPERATIONAL", "types": ["supermarket", "grocery_or_supermarket", "food", "point_of_interest", "store", "establishment"], "icon": "https://maps.gstatic.com/mapfiles/place_api/icons/v1/png_71/shopping-71.png"}, {"rating": 3.6, "user_ratings_total": 5, "name": "Behtar Enabled Sudhama Nagar", "reference": "ChIJucXrOloVrjsRTklkuFotrMY", "geometry": {"location": {"lat": 12.9576435, "lng": 77.5886424}, "viewport": {"northeast": {"lat": 12.9590093802915, "lng": 77.58999753029151}, "southwest": {"lat": 12.9563114197085, "lng": 77.5872995697085}}}, "place_id": "ChIJucXrOloVrjsRTklkuFotrMY", "plus_code": {"global_code": "7J4VXH5Q+3F", "compound_code": "XH5Q+3F Bengaluru, Karnataka, India"}, "vicinity": "20, 1st Main Road, Sudhama Nagar, Bengaluru", "photos": [{"photo_reference": "ATtYBwJOFDG3yMVrjF6bJA2CxE6byLvTaRwRcvv3h3CPD2xcpYj9mZFpjXU2uhF4jPMH73W6p1lnJjAC_Z0JBMY45HGu_fzLWv7u1GFixUtDR53s4ymmab5n0pXTb-C8nlRGWI6yUC3mJpiKN9eFTNGtjnk1ckCFrdVyYTPNaaxe_RjhaJTw", "width": 1944, "html_attributions": ["<a href=\"https://maps.google.com/maps/contrib/109844618988248612018\">Anu sachin</a>"], "height": 2592}], "scope": "GOOGLE", "business_status": "OPERATIONAL", "types": ["supermarket", "grocery_or_supermarket", "food", "point_of_interest", "store", "establishment"], "icon": "https://maps.gstatic.com/mapfiles/place_api/icons/v1/png_71/shopping-71.png"}, {"rating": 3.7, "user_ratings_total": 137, "name": "ALANKAR(GIFTS AND COSMETICS)", "reference": "ChIJEQ8rwtAVrjsRswY2NPCGXN4", "geometry": {"location": {"lat": 12.9602613, "lng": 77.5980871}, "viewport": {"northeast": {"lat": 12.9616161802915, "lng": 77.5993973802915}, "southwest": {"lat": 12.9589182197085, "lng": 77.5966994197085}}}, "opening_hours": {"open_now": true}, "place_id": "ChIJEQ8rwtAVrjsRswY2NPCGXN4", "plus_code": {"global_code": "7J4VXH6X+46", "compound_code": "XH6X+46 Bengaluru, Karnataka, India"}, "vicinity": "9, 5th Cross Road, Bheemanna Garden, Lakshmiamma Garden, Shanti Nagar, Bengaluru", "photos": [{"photo_reference": "ATtYBwKHFCIDCTcO12u2qy-i_VAFH7ir0BONWdRS0mra7RKWdXNaRCeHtwr9xl8s4YpITJZtx6IrN0VRrDL5u-Cs3sYpLQi14BGzGrFuaplBfbieJvtzr8Fnx8FpX9q_-637uDeNB4DCHDBQPlmR_tYP0a6iYnw0sNHm-SzDReD6MKSfCO0p", "width": 3120, "html_attributions": ["<a href=\"https://maps.google.com/maps/contrib/104863929750795569342\">harshith d</a>"], "height": 4160}], "scope": "GOOGLE", "business_status": "OPERATIONAL", "types": ["supermarket", "grocery_or_supermarket", "food", "point_of_interest", "store", "establishment"], "icon": "https://maps.gstatic.com/mapfiles/place_api/icons/v1/png_71/shopping-71.png"}, {"name": "Bbt street", "reference": "ChIJm57SIX8XrjsRbwl7dAo7d6M", "geometry": {"location": {"lat": 12.9675663, "lng": 77.5773627}, "viewport": {"northeast": {"lat": 12.9690101302915, "lng": 77.5787575302915}, "southwest": {"lat": 12.9663121697085, "lng": 77.57605956970849}}}, "place_id": "ChIJm57SIX8XrjsRbwl7dAo7d6M", "plus_code": {"global_code": "7J4VXH9G+2W", "compound_code": "XH9G+2W Bengaluru, Karnataka, India"}, "vicinity": "no 14 1 st cross, Belli Basavangudi Street, Mamulpet, Bengaluru", "scope": "GOOGLE", "business_status": "OPERATIONAL", "types": ["supermarket", "grocery_or_supermarket", "food", "point_of_interest", "store", "establishment"], "icon": "https://maps.gstatic.com/mapfiles/place_api/icons/v1/png_71/shopping-71.png"}, {"permanently_closed": true, "name": "STELCO ENTERPRISES", "reference": "ChIJh_dG5-MVrjsRgk0bSUGB5hU", "geometry": {"location": {"lat": 12.962058, "lng": 77.57982}, "viewport": {"northeast": {"lat": 12.9634017302915, "lng": 77.5811686302915}, "southwest": {"lat": 12.9607037697085, "lng": 77.57847066970848}}}, "place_id": "ChIJh_dG5-MVrjsRgk0bSUGB5hU", "plus_code": {"global_code": "7J4VXH6H+RW", "compound_code": "XH6H+RW Bengaluru, Karnataka, India"}, "vicinity": "46, New Gangammachari Street,, Mothinagar,, Bengaluru", "photos": [{"photo_reference": "ATtYBwKOmjiFRBvBZjjArY214DSe6lTf3U7IqKfQgT2QvqZchH1mvgRmwaFBxPM721WhHFAj1bleZp7TUqQVN9UF2_811WnyGcCKYYkUKAz16Uk6ViIhAO6WzLhpsIKJ7QKuymt0P0EWESLnDXNNSfDxfJgkdV1qV_tRaMYPDU8kfwHhftqh", "width": 3264, "html_attributions": ["<a href=\"https://maps.google.com/maps/contrib/102646882872694952765\">STELCO ENTERPRISES</a>"], "height": 2448}], "scope": "GOOGLE", "business_status": "CLOSED_TEMPORARILY", "types": ["supermarket", "grocery_or_supermarket", "food", "point_of_interest", "store", "establishment"], "icon": "https://maps.gstatic.com/mapfiles/place_api/icons/v1/png_71/generic_business-71.png"}]}